Workbook

Sheet STATS & KPIs
B2: ='FORM A'!A6 -> CONTRACT : ZNT 1129 | F2: SUMMARY OF MONTHLY STATISTICS
J3: ='FORM A'!E6 -> OPERATOR : | K3: ='FORM A'!F6 -> Ripple Effect 40 (Pty) Ltd
B4: ='FORM A'!C3 -> PROVISION OF PUBLIC PASSENGER TRANSPORT MKUZE AND SURROUNDING
J5: ='FORM A'!E8 -> FOR MONTH : | K5: ='FORM A'!F8 -> 45778
D8: SUBSIDISED SERVICES | G8: UNSUBSIDISED SERVICES | J8: SUBTOTAL | M8: TOTAL
D9: Standard buses | E9: Maxi buses | F9: Train Buses | G9: Standard buses | H9: Maxi buses | I9: Train Buses | J9: Standard buses | K9: Maxi buses | L9: Train Buses | M9: All services & vehicles
B10: 1 | C10: Operational statistics
B11: 1.1 | C11: Number of buses operated | D11: =SUM(D12:D13) -> 38 | J11: =SUM(D11+G11) -> 38 | K11: =SUM(E11+H11) -> 0 | L11: =SUM(F11+I11) -> 0 | M11: =SUM(J11:L11) -> 38
C12: Peak vehicle requirement: | D12: 21 | J12: =SUM(D12+G12) -> 21 | K12: =SUM(E12+H12) -> 0 | L12: =SUM(F12+I12) -> 0 | M12: =SUM(J12:L12) -> 21
C13: Spare buses: | D13: 17 | J13: =SUM(D13+G13) -> 17 | K13: =SUM(E13+H13) -> 0 | L13: =SUM(F13+I13) -> 0 | M13: =SUM(J13:L13) -> 17
B14: 1.2 | C14: Number of routes operated | D14: =COUNT('FORM F1 SUB - STD BUS'!L17:L56) -> 40 | G14: =COUNT('FORM F2 UNSUB - STD BUS '!F17:F21) -> 5 | J14: =SUM(D14+G14) -> 45 | K14: =SUM(E14+H14) -> 0 | L14: =SUM(F14+I14) -> 0 | M14: =SUM(J14:L14) -> 45
B15: 1.3 | C15: Number of staff | D15: 0 | G15: 0 | J15: =SUM(D15+G15) -> 0 | K15: =SUM(E15+H15) -> 0 | L15: =SUM(F15+I15) -> 0 | M15: =SUM(J15:L15) -> 0
B16: 1.4 | C16: Number of trips scheduled | D16: ='FORM F1 SUB - STD BUS'!F58 -> 998 | G16: ='FORM F2 UNSUB - STD BUS '!F23 -> 164 | J16: =SUM(D16+G16) -> 1162 | K16: =SUM(E16+H16) -> 0 | L16: =SUM(F16+I16) -> 0 | M16: =SUM(J16:L16) -> 1162
B17: 1.5 | C17: Number of trips operated | D17: ='FORM F1 SUB - STD BUS'!K58 -> 996 | G17: ='FORM F2 UNSUB - STD BUS '!K23 -> 164 | J17: =SUM(D17+G17) -> 1160 | K17: =SUM(E17+H17) -> 0 | L17: =SUM(F17+I17) -> 0 | M17: =SUM(J17:L17) -> 1160
B18: 1.6 | C18: Kilometres scheduled | D18: ='FORM F1 SUB - STD BUS'!M58 -> 82763.4 | G18: ='FORM F2 UNSUB - STD BUS '!M23 -> 16345.2 | J18: =SUM(D18+G18) -> 99108.6 | K18: =SUM(E18+H18) -> 0 | L18: =SUM(F18+I18) -> 0 | M18: =SUM(J18:L18) -> 99108.6
B19: 1.7 | C19: Kilometres operated | D19: ='FORM F1 SUB - STD BUS'!N58 -> 82529.4 | G19: ='FORM F2 UNSUB - STD BUS '!N23 -> 16345.2 | J19: =SUM(D19+G19) -> 98874.6 | K19: =SUM(E19+H19) -> 0 | L19: =SUM(F19+I19) -> 0 | M19: =SUM(J19:L19) -> 98874.6
B20: 1.8 | C20: Standing kilometres claimed | D20: ='FORM F1 SUB - STD BUS'!Z58 -> 234 | G20: 0 | J20: =D20 -> 234 | K20: =E20 -> 0 | L20: =F20 -> 0 | M20: =SUM(J20:L20) -> 234
B21: 1.9 | C21: Total no of passengers conveyed | D21: =SUM(D22:D23) -> 58044 | G21: =SUM(G22:G23) -> 6635 | J21: =SUM(D21+G21) -> 64679 | K21: =SUM(E21+H21) -> 0 | L21: =SUM(F21+I21) -> 0 | M21: =SUM(J21:L21) -> 64679
C22: - Number of cash passengers conveyed | D22: ='FORM F1 SUB - STD BUS'!O58 -> 58044 | G22: ='FORM F2 UNSUB - STD BUS '!O23 -> 6635 | J22: =SUM(D22+G22) -> 64679 | K22: =SUM(E22+H22) -> 0 | L22: =SUM(F22+I22) -> 0 | M22: =SUM(J22:L22) -> 64679
C23: - Number of MJT passengers conveyed | D23: ='FORM F1 SUB - STD BUS'!P58 -> 0 | G23: ='FORM F2 UNSUB - STD BUS '!P23 -> 0 | J23: =SUM(D23+G23) -> 0 | K23: =SUM(E23+H23) -> 0 | L23: =SUM(F23+I23) -> 0 | M23: =SUM(J23:L23) -> 0
B26: 2 | C26: Revenue
B27: 2.1 | C27: Total passenger revenue | D27: =SUM(D28:D29) -> 1023296 | F27: =SUM(F28:F29) -> 0 | G27: =G28+G29 -> 92290.5 | I27: =SUM(I28:I29) -> 0 | J27: =SUM(D27+G27) -> 1115586.5 | K27: =SUM(E27+H27) -> 0 | L27: =SUM(F27+I27) -> 0 | M27: =SUM(J27:L27) -> 1115586.5
C28: - Income from cash passengers | D28: ='FORM F1 SUB - STD BUS'!S58 -> 1023296 | G28: ='FORM F2 UNSUB - STD BUS '!S23 -> 92290.5 | I28: 0 | J28: =SUM(D28+G28) -> 1115586.5 | K28: =SUM(E28+H28) -> 0 | L28: =SUM(F28+I28) -> 0 | M28: =SUM(J28:L28) -> 1115586.5
C29: - Income from MJT passengers | D29: ='FORM F1 SUB - STD BUS'!T58 -> 0 | G29: ='FORM F2 UNSUB - STD BUS '!T23 -> 0 | I29: 0 | J29: =SUM(D29+G29) -> 0 | K29: =SUM(E29+H29) -> 0 | L29: =SUM(F29+I29) -> 0 | M29: =SUM(J29:L29) -> 0
B30: 2.2 | C30: Income from private hires | D30: N/A | F30: N/A | I30: 0 | J30: =G30 -> 0 | K30: =H30 -> 0 | L30: =I30 -> 0 | M30: =SUM(J30:L30) -> 0
B31: 2.3 | C31: Income from dedicated contracts | D31: N/A | F31: N/A | I31: 0 | J31: =G31 -> 0 | K31: =H31 -> 0 | L31: =I31 -> 0 | M31: =SUM(J31:L31) -> 0
B32: 2.4 | C32: Subsidy claimed | D32: ='FORM A'!H15 -> 3308835 | I32: N/A | J32: =D32 -> 3308835 | K32: =E32 -> 0 | L32: =F32 -> 0 | M32: =SUM(J32:L32) -> 3308835
B33: 2.5 | C33: Total income | D33: =SUM(D28:D32) -> 4332131 | I33: =SUM(I28:I32) -> 0 | J33: =SUM(J28:J32) -> 4424421.5 | K33: =SUM(K28:K32) -> 0 | L33: =SUM(L28:L32) -> 0 | M33: =SUM(J33:L33) -> 4424421.5
B36: 3 | C36: Penalties | D36: Number | E36: % of penalties | F36: Value of penalties before escalation | G36: Escalation Factor* | H36: Total value of penalties including escalation
B37: 3.1 | C37: Total penalties | D37: ='FORM G2'!E35 -> 9 | E37: 0 | F37: ='FORM G2'!I35 -> 1889.34 | G37: ='FORM C'!#REF! -> #REF! | H37: =F37*G37 -> #REF!
B38: 3.2 | C38: Penalties for trips not operated | D38: =SUM('FORM G2'!E16:E18) -> 9 | E38: 0 | F38: =SUM('FORM G2'!I16:I18) -> 1889.34 | G38: =G37 -> #REF! | H38: =F38*G38 -> #REF! | I38: `
B39: 3.3 | C39: Penalties for time related offences | D39: =SUM('FORM G2'!E19:E21) -> 0 | E39: 0 | F39: =SUM('FORM G2'!I19:I21) -> 0 | G39: =G37 -> #REF! | H39: =F39*G39 -> #REF!
B40: 3.4 | C40: Penalties related to unsatisfactory vehicle condition | D40: =SUM('FORM G2'!E25:E28) -> 0 | E40: 0 | F40: =SUM('FORM G2'!I25:I28) -> 0 | G40: =G37 -> #REF! | H40: =F40*G40 -> #REF!
B41: 3.5 | C41: Penalties related to unroadworthy vehicles | D41: ='FORM G2'!E24 -> 0 | E41: 0 | F41: ='FORM G2'!I24 -> 0 | G41: =G37 -> #REF! | H41: =F41*G41 -> #REF!
B42: 3.6 | C42: Penalties related to stop & route adherence | D42: ='FORM G2'!E29+'FORM G2'!E31 -> 0 | E42: 0 | F42: ='FORM G2'!I29+'FORM G2'!I31 -> 0 | G42: =G37 -> #REF! | H42: =F42*G42 -> #REF!
B43: 3.7 | C43: Penalties related to duty & destination boards | D43: ='FORM G2'!E23 -> 0 | E43: 0 | F43: ='FORM G2'!I23 -> 0 | G43: =G37 -> #REF! | H43: =F43*G43 -> #REF!
B44: * Link to be changed monthly to reflect escalation factor applicable
B47: 4 | C47: DORA KPIs for subsidised services | D47: Inception values | E47: Output values | F47: Performance value (%)
B48: 4.1 | C48: Number of vehicles subsidised | D48: =+D12+E12+F12 -> 21 | E48: =D11+E11+F11 -> 38 | F48: =(E48-D48)/D48 -> 0.80952381
B49: 4.2 | C49: Number of subsidised routes operated | F49: =(E49-D49)/D49 -> #DIV/0!
B50: 4.3 | C50: Staff/vehicle | D50: =SUM(D15:F15)/SUM(D12:F12) -> 0 | E50: =SUM(D15:F15)/E48 -> 0 | F50: =(E50-D50)/D50 -> #DIV/0!
B51: 4.4 | C51: Number of vehicle kms subsidised | D51: =SUM(D19:F19)/SUM(D12:F12) -> 3929.9714 | E51: =D51 -> 3929.9714 | F51: =(E51-D51)/D51 -> 0
B52: 4.5 | C52: Subsidy/vehicle | D52: =SUM(D32:F32)/SUM(D11:F11) -> 87074.604 | E52: =D52 -> 87074.604 | F52: =(E52-D52)/D52 -> 0
B53: 4.6 | C53: Subsidy/passenger | D53: =SUM(D32:F32)/SUM(D21:F21) -> 57.005633 | E53: =D53 -> 57.005633 | F53: =(E53-D53)/D53 -> 0
B54: 4.7 | C54: Subsidy/kilometre operated | D54: =SUM(D32:F32)/SUM(D19:F19) -> 40.092803 | E54: =D54 -> 40.092803 | F54: =(E54-D54)/D54 -> 0
B55: 4.8 | C55: Kilometres operated/vehicle | D55: =SUM(D19:F19)/SUM(D12:F12) -> 3929.9714 | E55: =D55 -> 3929.9714 | F55: =(E55-D55)/D55 -> 0
B56: 4.9 | C56: Passengers/ vehicle | D56: =SUM(D21:F21)/SUM(D12:F12) -> 2764 | E56: =D56 -> 2764 | F56: =(E56-D56)/D56 -> 0
B57: 4.1 | C57: Passengers/ trip operated | D57: =SUM(D21:F21)/SUM(D17:F17) -> 58.277108 | E57: =D57 -> 58.277108 | F57: =(E57-D57)/D57 -> 0
B58: 4.11 | C58: Passenger revenue/vehicle | D58: =SUM(D27:F27)/SUM(D11:F11) -> 26928.842 | E58: =D58 -> 26928.842 | F58: =(E58-D58)/D58 -> 0
B59: 4.12 | C59: Passenger revenue/trip operated | D59: =SUM(D27:F27)/SUM(D17:F17) -> 1027.4056 | E59: =D59 -> 1027.4056 | F59: =(E59-D59)/D59 -> 0

Sheet FORM A
A1: FORM A
A3: PUBLIC TRANSPORT : | C3: PROVISION OF PUBLIC PASSENGER TRANSPORT MKUZE AND SURROUNDING
A6: CONTRACT : ZNT 1129 | E6: OPERATOR : | F6: Ripple Effect 40 (Pty) Ltd
A8: PAYMENT CERTIFICATE NO.: | C8: 320 | E8: FOR MONTH : | F8: 45778
A11: ACCUMULATED ESCALATED CONTRACT AMOUNT | E11: (FORM C, Col 7) | H11: =+'FORM C'!G337 -> 6.256782e+08
A13: LESS ACCUMULATED CERTIFICATE VALUES | E13: (FORM B, Col 5) | H13: ='FORM B'!E339 -> 6.2236936e+08
E15: SUB TOTAL 1 | H15: =SUM(H11-H13) -> 3308835
A20: DEDUCT REFUNDABLE PENALTIES IMPOSED FOR
A21: NON-COMPLIANCE WITH SERVICE SPECIFICATIONS :
A23: % FOR APPROVED VEHICLES NOT OPERATED (SCC - CL 5.5.8 (a)) | F23: 0
A25: % FOR TICKET MACHINES NOT USED (SCC - CL 5.5.9) | F25: 0
A27: % FOR MONTHLY STATISTICS NOT SUPPLIED (SCC - CL 5.5.9 (c)) | F27: 0
A29: % FOR FAILURE TO IMPLEMENT RDP PROPOSAL (SCC - CL5.510) | F29: 0
A31: % FOR FAILURE TO IMPLEMENT VIABLE SUB-CONTRACTING | F31: 0
E33: SUB TOTAL 2 | F33: =SUM(F18:F31) -> 0
A35: RELEASE REFUNDABLE PENALTIES IMPOSED FOR
A36: NON-COMPLIANCE WITH SERVICE SPECIFICATIONS :
A38: 5% FOR APPROVED VEHICLES NOT OPERATED (SCC - CL 5.5.8 (a)) | G38: 0
A40: 3% FOR APPROVED EE NOT USED (SCC - CL 5.5.9 (b)) | G40: 0
A42: 5% FOR MONTHLY STATISTICS NOT SUPPLIED (SCC - CL 5.5.9 (c)) | G42: 0
A44: 3% FOR FAILURE TO IMPLEMENT RDP PROPOSAL (SCC - CL5.5.10) | G44: 0
A46: 5% FOR FAILURE TO IMPLEMENT VIABLE SUB-CONTRACTING | G46: 0
E49: SUB TOTAL 3 | G49: =SUM(G38:G46) -> 0
A50: BANKDETAILS:
A51: Accountholder name: | B51: Ripple Effect 40 Close Corporation
A52: Account type: | B52: Cheque
A53: Account number: | B53: 50913212
A54: Bank: | B54: STANDARDBANK SA
A55: Branch name: | B55: KINGSMEAD
A56: Branch code: | B56: 40026
A59: TOTAL AMOUNT DUE | H59: =H15-F33+G49 -> 3308835
A62: On behalf of Ripple Effect 40 (PTY) LTD it is herewith certified that the information supplied in this
A63: Monthly Claim Form is correct and just.
A66: …………………………………………………………………………………………………… | G66: ………………………………..
A67: OPERATOR | G67: DATE
A69: …………………………………………………………………………………………………… | G69: ………………………………..
A70: CERTIFIED BY THE REPRESENTATIVE | G70: DATE
A73: ………………………………………………………………………………………………….. | G73: ………………………………..
A74: CERTIFIED : DEPARTMENT OF TRANSPORT | G74: DATE
A76: PAYMENT OF | B76: R.............................……… | D76: APPROVED BY
A78: …………………………………………………………………. | G78: ………………………………..
A79: DEPARTMENT OF TRANSPORT | G79: DATE

Sheet FORM B
A1: FORM B
A3: PUBLIC TRANSPORT : | C3: ='FORM A'!C3 -> PROVISION OF PUBLIC PASSENGER TRANSPORT MKUZE AND SURROUNDING
A5: ='FORM A'!A6 -> CONTRACT : ZNT 1129 | E5: OPERATOR : | F5: ='FORM A'!F6 -> Ripple Effect 40 (Pty) Ltd
A7: PAYMENT CERTIFICATE NO.: | C7: ='FORM A'!C8 -> 320 | E7: FOR MONTH : | F7: ='FORM A'!F8 -> 45778
A9: RECORD OF PAYMENTS | E9: ESTABLISHMENT COST PAID: | G9: 0
F11: Deduction of | G11: Release of | I11: Contributions
A12: Certificate | B12: Month | C12: Year | D12: Cert | E12: Accumulated | F12: refundable | G12: refundable | H12: Amounts | I12: paid to Bus
A13: number | D13: value | E13: certified values | F13: penalties or | G13: penalties or | H13: paid to | I13: Restructuring
F14: PTOG deductions | G14: PTOG deductions | H14: Operator | I14: Fund
A15: 1 | B15: 2 | C15: 3 | D15: 4 | E15: 5 | F15: 6 | G15: 7 | H15: 8 | I15: 9
A16: OLD PC SYSTEM PC ADJUST FOR REFUNDABLE PEN ETC. | E16: 5505132.4
A17: 1 | B17: November | C17: 1998 | D17: 663682.91 | E17: =D17 -> 663682.91 | H17: =D17 -> 663682.91
A18: =A17+1 -> 2 | B18: December | C18: 1998 | D18: 552711.48 | E18: =D18 -> 552711.48 | H18: =D18 -> 552711.48
A19: =A18+1 -> 3 | B19: January | C19: 1999 | D19: 636065.72 | E19: =D19 -> 636065.72 | H19: =D19 -> 636065.72
A20: =A19+1 -> 4 | B20: February | C20: 1999 | D20: 615122.13 | E20: =D20 -> 615122.13 | H20: =D20 -> 615122.13
A21: =A20+1 -> 5 | B21: March | C21: 1999 | D21: 687738.4 | E21: =D21 -> 687738.4 | H21: =D21 -> 687738.4
A22: =A21+1 -> 6 | B22: April | C22: 1999 | D22: 335237.7 | E22: =D22 -> 335237.7 | H22: =D22 -> 335237.7
A23: =A22+1 -> 7 | B23: May | C23: 1999 | D23: 606701.39 | E23: =D23 -> 606701.39 | H23: =D23 -> 606701.39
A24: =A23+1 -> 8 | B24: June | C24: 1999 | D24: 632266.31 | E24: =D24 -> 632266.31 | H24: =D24 -> 632266.31
A25: =A24+1 -> 9 | B25: July | C25: 1999 | D25: 861564.1 | E25: =D25 -> 861564.1 | H25: =D25 -> 861564.1
A26: =A25+1 -> 10 | B26: August | C26: 1999 | D26: 694941.72 | E26: =D26 -> 694941.72 | H26: =D26 -> 694941.72
A27: =A26+1 -> 11 | B27: September | C27: 1999 | D27: 753476.86 | E27: =D27 -> 753476.86 | H27: =D27 -> 753476.86
A28: =A27+1 -> 12 | B28: October | C28: 1999 | D28: 691530.92 | E28: =D28 -> 691530.92 | H28: =D28 -> 691530.92
A29: =A28+1 -> 13 | B29: November | C29: 1999 | D29: 778922.04 | E29: =D29 -> 778922.04 | H29: =D29 -> 778922.04
... A256: =A255+1 -> 240 | B256: September | C256: 2018 | D256: 2712031.3 | E256: =D256 -> 2712031.3 | H256: =D256 -> 2712031.3
A257: =A256+1 -> 241 | B257: October | C257: 2018 | D257: 2554974.2 | E257: =D257 -> 2554974.2 | H257: =D257 -> 2554974.2 | J257: Penalties deducted INCORRECTLY in JUNE
A258: =A257+1 -> 242 | B258: November | C258: 2018 | D258: 2856222.3 | E258: =D258 -> 2856222.3 | H258: =D258 -> 2856222.3
A259: =A258+1 -> 243 | B259: December | C259: 2018 | D259: 2797098.2 | E259: =D259 -> 2797098.2 | H259: =D259 -> 2797098.2 | J259: 45089 | K259: 5 | L259: 15 | M259: 1100 | N259: 0.45833333 | O259: MKUZE | P259: MKUZE | Q259: EKUKHANYENI | R259: 4 | S259: 117 | T259: 8.21 | U259: 0.4 | V259: =ROUND(S259*T259*U259,2) -> 384.23
A260: =A259+1 -> 244 | B260: January | C260: 2019 | D260: 2609454.3 | E260: =D260 -> 2609454.3 | H260: =D260 -> 2609454.3 | J260: 45089 | K260: 1B.1 | L260: 1 | M260: 1100 | N260: 0.45833333 | O260: MKUZE | P260: MKUZE | Q260: EMACHOBENI | R260: 4 | S260: 90 | T260: 8.21 | U260: 0.4 | V260: =ROUND(S260*T260*U260,2) -> 295.56
A261: =A260+1 -> 245 | B261: February | C261: 2019 | D261: 2417774.9 | E261: =D261 -> 2417774.9 | H261: =D261 -> 2417774.9 | J261: 45089 | K261: 7A | L261: 21 | M261: 1100 | N261: 0.45833333 | O261: MKUZE | P261: MKUZE | Q261: MANGUZE | R261: 4 | S261: 136.5 | T261: 8.21 | U261: 0.4 | V261: =ROUND(S261*T261*U261,2) -> 448.27
A262: =A261+1 -> 246 | B262: March | C262: 2019 | D262: 2566595.1 | E262: =D262 -> 2566595.1 | H262: =D262 -> 2566595.1 | J262: 45089 | K262: 6A | L262: 17 | M262: 1200 | N262: 0.5 | O262: MKUZE | P262: MKUZE | Q262: MANGUZE | R262: 4 | S262: 149.9 | T262: 8.21 | U262: 0.4 | V262: =ROUND(S262*T262*U262,2) -> 492.27
A263: =A262+1 -> 247 | B263: April | C263: 2019 | D263: 2638118.5 | E263: =D263 -> 2638118.5 | H263: =D263 -> 2638118.5 | J263: 45089 | K263: 9A | L263: 25 | M263: 1200 | N263: 0.5 | O263: MKUZE | P263: MKUZE | Q263: MAZIBUKO | R263: 4 | S263: 70.3 | T263: 8.21 | U263: 0.4 | V263: =ROUND(S263*T263*U263,2) -> 230.87
A264: =A263+1 -> 248 | B264: May | C264: 2019 | D264: 2768870.1 | E264: =D264 -> 2768870.1 | H264: =D264 -> 2768870.1 | J264: 45089 | K264: 8 | L264: 24mth | M264: 1230 | N264: 0.52083333 | O264: MKUZE | P264: MKUZE | Q264: MANABA | R264: 4 | S264: 78.8 | T264: 8.21 | U264: 0.4 | V264: =ROUND(S264*T264*U264,2) -> 258.78
A265: =A264+1 -> 249 | B265: June | C265: 2019 | D265: 2751264.1 | E265: =D265 -> 2751264.1 | H265: =D265 -> 2751264.1 | J265: 45089 | K265: 1A4 | L265: 19 | M265: 1300 | N265: 0.54166667 | O265: MKUZE | P265: MKUZE | Q265: MAVELA | R265: 4 | S265: 35.8 | T265: 8.21 | U265: 0.4 | V265: =ROUND(S265*T265*U265,2) -> 117.57
A266: =A265+1 -> 250 | B266: July | C266: 2019 | D266: 2729541.8 | E266: =D266 -> 2729541.8 | H266: =D266 -> 2729541.8 | J266: 45089 | K266: 7C | L266: 22 | M266: 1300 | N266: 0.54166667 | O266: MKUZE | P266: MKUZE | Q266: NGUTSHANA | R266: 4 | S266: 117.5 | T266: 8.21 | U266: 0.4 | V266: =ROUND(S266*T266*U266,2) -> 385.87
A267: =A266+1 -> 251 | B267: August | C267: 2019 | D267: 2738515.6 | E267: =D267 -> 2738515.6 | H267: =D267 -> 2738515.6 | J267: 45089 | K267: 1A1 | L267: 2 | M267: 1400 | N267: 0.58333333 | O267: MKUZE | P267: MKUZE | Q267: EMACHOBENI | R267: 4 | S267: 90 | T267: 8.21 | U267: 0.4 | V267: =ROUND(S267*T267*U267,2) -> 295.56
A268: =A267+1 -> 252 | B268: September | C268: 2019 | D268: 2780375.1 | E268: =D268 -> 2780375.1 | H268: =D268 -> 2780375.1 | J268: 45089 | K268: 9B | L268: 26 | M268: 1400 | N268: 0.58333333 | O268: MKUZE | P268: MKUZE | Q268: HLABISA | R268: 4 | S268: 78 | T268: 8.21 | U268: 0.4 | V268: =ROUND(S268*T268*U268,2) -> 256.15
A269: =A268+1 -> 253 | B269: October | C269: 2019 | D269: 2634787.8 | E269: =D269 -> 2634787.8 | H269: =D269 -> 2634787.8 | J269: 45089 | K269: 6B | L269: 18 | M269: 1640 | N269: 0.69444444 | O269: MKUZE | P269: MKUZE | Q269: MBUYISA | R269: 4 | S269: 97.5 | T269: 8.21 | U269: 0.4 | V269: =ROUND(S269*T269*U269,2) -> 320.19
A270: =A269+1 -> 254 | B270: November | C270: 2019 | D270: 2776691.6 | E270: =D270 -> 2776691.6 | H270: =D270 -> 2776691.6 | J270: 45089 | K270: 6C | L270: 19 | M270: 1730 | N270: 0.72916667 | O270: MKUZE | P270: MKUZE | Q270: JOZINI | R270: 4 | S270: 41 | T270: 8.21 | U270: 0.4 | V270: =ROUND(S270*T270*U270,2) -> 134.64
A271: =A270+1 -> 255 | B271: December | C271: 2019 | D271: 2646984.4 | E271: =D271 -> 2646984.4 | H271: =D271 -> 2646984.4 | J271: 45090 | K271: 1B2 | L271: 3 | M271: 600 | N271: 0.36111111 | O271: MKUZE | P271: MKUZE | Q271: INGWAVUMA | R271: 4 | S271: 85.3 | T271: 8.21 | U271: 0.4 | V271: =ROUND(S271*T271*U271,2) -> 280.13
A272: =A271+1 -> 256 | B272: January | C272: 2020 | D272: 2793420 | E272: =D272 -> 2793420 | H272: =D272 -> 2793420 | J272: 45090 | K272: 6C | L272: 19 | M272: 600 | N272: 0.30902778 | O272: MKUZE | P272: JOZINI | Q272: MKUZE | R272: 4 | S272: 41 | T272: 8.21 | U272: 0.4 | V272: =ROUND(S272*T272*U272,2) -> 134.64
A273: =A272+1 -> 257 | B273: February | C273: 2020 | D273: 2839432.6 | E273: =D273 -> 2839432.6 | H273: =D273 -> 2839432.6 | J273: 45090 | K273: 1A1 | L273: 1 | M273: 620 | N273: 0.36805556 | O273: MKUZE | P273: EMACHOBENI | Q273: MKUZE | R273: 4 | S273: 81.8 | T273: 8.21 | U273: 0.4 | V273: =ROUND(S273*T273*U273,2) -> 268.63
A274: =A273+1 -> 258 | B274: March | C274: 2020 | D274: 2758811.6 | E274: =D274 -> 2758811.6 | H274: =D274 -> 2758811.6 | J274: 45090 | K274: 6A | L274: 16 | M274: 500 | N274: 0.375 | O274: MKUZE | P274: MANGUZE | Q274: MKUZE | R274: 4 | S274: 149.9 | T274: 8.21 | U274: 0.4 | V274: =ROUND(S274*T274*U274,2) -> 492.27
A275: =A274+1 -> 259 | B275: April | C275: 2020 | D275: 1656759.1 | E275: =D275 -> 1656759.1 | H275: =D275 -> 1656759.1 | J275: 45090 | K275: 6B | L275: 18 | M275: 600 | N275: 0.375 | O275: MKUZE | P275: MBUYISA | Q275: MKUZE | R275: 4 | S275: 97.5 | T275: 8.21 | U275: 0.4 | V275: =ROUND(S275*T275*U275,2) -> 320.19
A276: =A275+1 -> 260 | B276: May | C276: 2020 | D276: 2376903.4 | E276: =D276 -> 2376903.4 | H276: =D276 -> 2376903.4 | J276: 45090 | K276: 9A | L276: 25 | M276: 600 | N276: 0.375 | O276: MKUZE | P276: MAZIBUKO | Q276: MKUZE | R276: 4 | S276: 70.3 | T276: 8.21 | U276: 0.4 | V276: =ROUND(S276*T276*U276,2) -> 230.87
A277: 261 | B277: June | C277: 2020 | D277: 2366868.4 | E277: =D277 -> 2366868.4 | H277: =D277 -> 2366868.4 | J277: 45090 | K277: 9B | L277: 26 | M277: 600 | N277: 0.375 | O277: MKUZE | P277: HLABISA | Q277: MKUZE | R277: 4 | S277: 78 | T277: 8.21 | U277: 0.4 | V277: =ROUND(S277*T277*U277,2) -> 256.15
A278: 262 | B278: July | C278: 2020 | D278: 2213598 | E278: =D278 -> 2213598 | H278: =D278 -> 2213598 | J278: 45090 | K278: 1A4 | L278: 19 | M278: 800 | N278: 0.375 | O278: MKUZE | P278: MAVELA | Q278: MKUZE | R278: 4 | S278: 35.8 | T278: 8.21 | U278: 0.4 | V278: =ROUND(S278*T278*U278,2) -> 117.57
A279: 263 | B279: August | C279: 2020 | D279: 2737288.4 | E279: =D279 -> 2737288.4 | H279: =D279 -> 2737288.4 | J279: 45090 | K279: 8 | L279: 24mth | M279: 600 | N279: 0.38888889 | O279: MKUZE | P279: MANABA | Q279: MKUZE | R279: 4 | S279: 78.8 | T279: 8.21 | U279: 0.4 | V279: =ROUND(S279*T279*U279,2) -> 258.78
A280: 264 | B280: September | C280: 2020 | D280: 2645362.2 | E280: =D280 -> 2645362.2 | H280: =D280 -> 2645362.2 | J280: 45090 | K280: 5 | L280: 15 | M280: 530 | N280: 0.39583333 | O280: MKUZE | P280: EKUKHANYENI | Q280: MKUZE | R280: 4 | S280: 117 | T280: 8.21 | U280: 0.4 | V280: =ROUND(S280*T280*U280,2) -> 384.23
A281: 265 | B281: October | C281: 2020 | D281: 2680357.9 | E281: =D281 -> 2680357.9 | H281: =D281 -> 2680357.9 | J281: 45090 | K281: 7C | L281: 22 | M281: 530 | N281: 0.39583333 | O281: MKUZE | P281: NGUTSHANA | Q281: MKUZE | R281: 4 | S281: 117.5 | T281: 8.21 | U281: 0.4 | V281: =ROUND(S281*T281*U281,2) -> 385.87
A282: 266 | B282: November | C282: 2020 | D282: 2469156.5 | E282: =D282 -> 2469156.5 | H282: =D282 -> 2469156.5 | J282: 45090 | K282: 5 | L282: 15 | M282: 1100 | N282: 0.45833333 | O282: MKUZE | P282: MKUZE | Q282: EKUKHANYENI | R282: 4 | S282: 117 | T282: 8.21 | U282: 0.4 | V282: =ROUND(S282*T282*U282,2) -> 384.23
A283: 267 | B283: December | C283: 2020 | D283: 2666220.5 | E283: =D283 -> 2666220.5 | H283: =D283 -> 2666220.5 | J283: 45090 | K283: 1B.1 | L283: 1 | M283: 1100 | N283: 0.45833333 | O283: MKUZE | P283: MKUZE | Q283: EMACHOBENI | R283: 4 | S283: 90 | T283: 8.21 | U283: 0.4 | V283: =ROUND(S283*T283*U283,2) -> 295.56
A284: 268 | B284: January | C284: 2021 | D284: 2543519.3 | E284: =D284 -> 2543519.3 | H284: =D284 -> 2543519.3 | J284: 45090 | K284: 7A | L284: 21 | M284: 1100 | N284: 0.45833333 | O284: MKUZE | P284: MKUZE | Q284: MANGUZE | R284: 4 | S284: 136.5 | T284: 8.21 | U284: 0.4 | V284: =ROUND(S284*T284*U284,2) -> 448.27
A285: 269 | B285: February | C285: 2021 | D285: 2481269.4 | E285: =D285 -> 2481269.4 | H285: =D285 -> 2481269.4 | J285: 45090 | K285: 1B.1 | L285: 2 | M285: 920 | N285: 0.49305556 | O285: MKUZE | P285: EMACHOBENI | Q285: MKUZE | R285: 4 | S285: 90 | T285: 8.21 | U285: 0.4 | V285: =ROUND(S285*T285*U285,2) -> 295.56
A286: 270 | B286: March | C286: 2021 | D286: 2695839 | E286: =D286 -> 2695839 | H286: =D286 -> 2695839 | J286: 45090 | K286: 6A | L286: 17 | M286: 1200 | N286: 0.5 | O286: MKUZE | P286: MKUZE | Q286: MANGUZE | R286: 4 | S286: 149.9 | T286: 8.21 | U286: 0.4 | V286: =ROUND(S286*T286*U286,2) -> 492.27
A287: 271 | B287: April | C287: 2021 | D287: 2796796.5 | E287: =D287 -> 2796796.5 | H287: =D287 -> 2796796.5 | J287: 45090 | K287: 9A | L287: 25 | M287: 1200 | N287: 0.5 | O287: MKUZE | P287: MKUZE | Q287: MAZIBUKO | R287: 4 | S287: 70.3 | T287: 8.21 | U287: 0.4 | V287: =ROUND(S287*T287*U287,2) -> 230.87
A288: 272 | B288: May | C288: 2021 | D288: 2800161.9 | E288: =D288 -> 2800161.9 | H288: =D288 -> 2800161.9 | J288: 45090 | K288: 8 | L288: 24mth | M288: 1230 | N288: 0.52083333 | O288: MKUZE | P288: MKUZE | Q288: MANABA | R288: 4 | S288: 78.8 | T288: 8.21 | U288: 0.4 | V288: =ROUND(S288*T288*U288,2) -> 258.78
A289: 273 | B289: June | C289: 2021 | D289: 2639490.4 | E289: =D289 -> 2639490.4 | H289: =D289 -> 2639490.4 | J289: 45090 | K289: 1A4 | L289: 19 | M289: 1300 | N289: 0.54166667 | O289: MKUZE | P289: MKUZE | Q289: MAVELA | R289: 4 | S289: 35.8 | T289: 8.21 | U289: 0.4 | V289: =ROUND(S289*T289*U289,2) -> 117.57
A290: 274 | B290: July | C290: 2021 | D290: 2637762.5 | E290: =D290 -> 2637762.5 | H290: =D290 -> 2637762.5 | J290: 45090 | K290: 7C | L290: 22 | M290: 1300 | N290: 0.54166667 | O290: MKUZE | P290: MKUZE | Q290: NGUTSHANA | R290: 4 | S290: 117.5 | T290: 8.21 | U290: 0.4 | V290: =ROUND(S290*T290*U290,2) -> 385.87
A291: 275 | B291: August | C291: 2021 | D291: 2818432.9 | E291: =D291 -> 2818432.9 | H291: =D291 -> 2818432.9 | J291: 45090 | K291: 1A1 | L291: 2 | M291: 1400 | N291: 0.58333333 | O291: MKUZE | P291: MKUZE | Q291: EMACHOBENI | R291: 4 | S291: 90 | T291: 8.21 | U291: 0.4 | V291: =ROUND(S291*T291*U291,2) -> 295.56
A292: 276 | B292: September | C292: 2021 | D292: 2839620.7 | E292: =D292 -> 2839620.7 | H292: =D292 -> 2839620.7 | J292: 45090 | K292: 9B | L292: 26 | M292: 1400 | N292: 0.58333333 | O292: MKUZE | P292: MKUZE | Q292: HLABISA | R292: 4 | S292: 78 | T292: 8.21 | U292: 0.4 | V292: =ROUND(S292*T292*U292,2) -> 256.15
A293: 277 | B293: October | C293: 2021 | D293: 3016442.9 | E293: =D293 -> 3016442.9 | H293: =D293 -> 3016442.9 | J293: 45090 | K293: 7A | L293: 20 | M293: 1000 | N293: 0.59375 | O293: MKUZE | P293: MANGUZE | Q293: MKUZE | R293: 4 | S293: 136.5 | T293: 8.21 | U293: 0.4 | V293: =ROUND(S293*T293*U293,2) -> 448.27
A294: 278 | B294: November | C294: 2021 | D294: 2937738.7 | E294: =D294 -> 2937738.7 | H294: =D294 -> 2937738.7 | J294: 45090 | K294: 1B2 | L294: 3 | M294: 1330 | N294: 0.67013889 | O294: MKUZE | P294: INGWAVUMA | Q294: MKUZE | R294: 4 | S294: 85.3 | T294: 8.21 | U294: 0.4 | V294: =ROUND(S294*T294*U294,2) -> 280.13
A295: 279 | B295: December | C295: 2021 | D295: 3135270.8 | E295: =D295 -> 3135270.8 | H295: =D295 -> 3135270.8 | J295: 45090 | K295: 6B | L295: 18 | M295: 1640 | N295: 0.69444444 | O295: MKUZE | P295: MKUZE | Q295: MBUYISA | R295: 4 | S295: 97.5 | T295: 8.21 | U295: 0.4 | V295: =ROUND(S295*T295*U295,2) -> 320.19
A296: 280 | B296: January | C296: 2022 | D296: 3109313.5 | E296: =D296 -> 3109313.5 | H296: =D296 -> 3109313.5 | J296: 45090 | K296: 6C | L296: 19 | M296: 1730 | N296: 0.72916667 | O296: MKUZE | P296: MKUZE | Q296: JOZINI | R296: 4 | S296: 41 | T296: 8.21 | U296: 0.4 | V296: =ROUND(S296*T296*U296,2) -> 134.64
A297: 281 | B297: February | C297: 2022 | D297: 2939961.5 | E297: =D297 -> 2939961.5 | H297: =D297 -> 2939961.5 | V297: =SUM(V259:V296) -> 11393.21
A298: 282 | B298: March | C298: 2022 | D298: 3082347 | E298: =D298 -> 3082347 | H298: =D298 -> 3082347
A299: 283 | B299: April | C299: 2022 | D299: 3346770.8 | E299: =D299 -> 3346770.8 | H299: =D299 -> 3346770.8
A300: 284 | B300: May | C300: 2022 | D300: 3407939.7 | E300: =D300 -> 3407939.7 | H300: =D300 -> 3407939.7
A301: 285 | B301: June | C301: 2022 | D301: 3398356.7 | E301: =D301 -> 3398356.7 | H301: =D301 -> 3398356.7
A302: 286 | B302: July | C302: 2022 | D302: 3651163.8 | E302: =D302 -> 3651163.8 | H302: =D302 -> 3651163.8
A303: 287 | B303: August | C303: 2022 | D303: 3953348.6 | E303: =D303 -> 3953348.6 | H303: =D303 -> 3953348.6
A304: 288 | B304: September | C304: 2022 | D304: 3502715.8 | E304: =D304 -> 3502715.8 | H304: =D304 -> 3502715.8
A305: 289 | B305: October | C305: 2022 | D305: 3606277.8 | E305: =D305 -> 3606277.8 | H305: =D305 -> 3606277.8
A306: 290 | B306: November | C306: 2022 | D306: 3641695.4 | E306: =D306 -> 3641695.4 | H306: =D306 -> 3641695.4
A307: 291 | B307: December | C307: 2022 | D307: 3915358.6 | E307: =D307 -> 3915358.6 | H307: =D307 -> 3915358.6
A308: 292 | B308: January | C308: 2023 | D308: 3436345.4 | E308: =D308 -> 3436345.4 | H308: =D308 -> 3436345.4
A309: 293 | B309: February | C309: 2023 | D309: 3058669.8 | E309: =D309 -> 3058669.8 | H309: =D309 -> 3058669.8
... A334: 318 | B334: March | C334: 2025 | D334: 3428452.8 | E334: =D334 -> 3428452.8 | H334: =D334 -> 3428452.8
A335: 319 | B335: April | C335: 2025 | D335: 3446304.9 | E335: =D335 -> 3446304.9 | F335: 3255015.4 | H335: =D335-F335 -> 191289.43
A336: 320 | B336: May | C336: 2025 | D336: ='FORM A'!H15 -> 3308835 | F336: 0 | H336: =D336-F336 -> 3308835
D339: TOTAL | E339: =SUM(E16:E338) -> 6.2236936e+08
D344: 4.3286934e+08 | E344: =D344-E339 -> -1.8950002e+08
E348: 72051648
E349: 460377.2

Sheet FORM C
A1: FORM C
A3: PUBLIC TRANSPORT : | C3: ='FORM A'!C3 -> PROVISION OF PUBLIC PASSENGER TRANSPORT MKUZE AND SURROUNDING
A5: ='FORM A'!A6 -> CONTRACT : ZNT 1129 | E5: OPERATOR : | F5: ='FORM A'!F6 -> Ripple Effect 40 (Pty) Ltd
A7: PAYMENT CERTIFICATE NO: | C7: ='FORM A'!C8 -> 320 | E7: FOR MONTH : | F7: ='FORM A'!F8 -> 45778
A9: ESCALATED MONTHLY CERTIFICATE
A12: Certificate | B12: Month | C12: Year | D12: Amount for | E12: Escalation | F12: Escalated | G12: Accumulated
A13: number | D13: Escalation | E13: Factor * | F13: Amount | G13: Total
D14: (Form E) | E14: (Form D) | F14: (4 x 5)
A15: 1 | B15: 2 | C15: 3 | D15: 4 | E15: 5 | F15: 6 | G15: 7
A16: 1 | B16: November | C16: 1998 | D16: 653079.7 | E16: ='FORM D'!G22 -> 1.025043 | F16: =ROUND(D16*E16,2) -> 669434.77 | G16: =SUM($F$16:F16) -> 669434.77
A17: =A16+1 -> 2 | B17: December | C17: 1998 | D17: 543881.18 | E17: ='FORM D'!G23 -> 1.018293 | F17: =ROUND(D17*E17,2) -> 553830.37 | G17: =SUM($F$16:F17) -> 1223265.1
A18: =A17+1 -> 3 | B18: January | C18: 1999 | D18: 626903.73 | E18: ='FORM D'!G24 -> 1.0186755 | F18: =ROUND(D18*E18,2) -> 638611.48 | G18: =SUM($F$16:F18) -> 1861876.6
A19: =A18+1 -> 4 | B19: February | C19: 1999 | D19: 600141.48 | E19: ='FORM D'!G25 -> 1.0301078 | F19: =ROUND(D19*E19,2) -> 618210.4 | G19: =SUM($F$16:F19) -> 2480087
A20: =A19+1 -> 5 | B20: March | C20: 1999 | D20: 575610.42 | E20: ='FORM D'!G26 -> 1.0293972 | F20: =ROUND(D20*E20,2) -> 592531.78 | G20: =SUM($F$16:F20) -> 3072618.8
A21: =A20+1 -> 6 | B21: April | C21: 1999 | D21: 399087.15 | E21: ='FORM D'!G27 -> 1.0480167 | F21: =ROUND(D21*E21,2) -> 418250 | G21: =SUM($F$16:F21) -> 3490868.8
A22: =A21+1 -> 7 | B22: May | C22: 1999 | D22: 594897.07 | E22: ='FORM D'!G28 -> 1.0626464 | F22: =ROUND(D22*E22,2) -> 632165.2 | G22: =SUM($F$16:F22) -> 4123034
A23: =A22+1 -> 8 | B23: June | C23: 1999 | D23: 655391 | E23: ='FORM D'!G29 -> 1.0697517 | F23: =ROUND(D23*E23,2) -> 701105.61 | G23: =SUM($F$16:F23) -> 4824139.6
A24: =A23+1 -> 9 | B24: July | C24: 1999 | D24: 664456.02 | E24: ='FORM D'!G30 -> 1.0933768 | F24: =ROUND(D24*E24,2) -> 726500.78 | G24: =SUM($F$16:F24) -> 5550640.4
A25: =A24+1 -> 10 | B25: August | C25: 1999 | D25: 632628.93 | E25: ='FORM D'!G31 -> 1.1097463 | F25: =ROUND(D25*E25,2) -> 702057.61 | G25: =SUM($F$16:F25) -> 6252698
A26: =A25+1 -> 11 | B26: September | C26: 1999 | D26: 633492.4 | E26: ='FORM D'!G32 -> 1.1236016 | F26: =ROUND(D26*E26,2) -> 711793.1 | G26: =SUM($F$16:F26) -> 6964491.1
A27: =A26+1 -> 12 | B27: October | C27: 1999 | D27: 664346.15 | E27: ='FORM D'!G33 -> 1.1356807 | F27: =ROUND(D27*E27,2) -> 754485.08 | G27: =SUM($F$16:F27) -> 7718976.2
A28: =A27+1 -> 13 | B28: November | C28: 1999 | D28: 676326.7 | E28: ='FORM D'!G34 -> 1.1445623 | F28: =ROUND(D28*E28,2) -> 774098.05 | G28: =SUM($F$16:F28) -> 8493074.2
... A275: =A274+1 -> 260 | B275: May | C275: 2020 | D275: 600823.58 | E275: ='FORM D'!G281 -> 3.722718 | F275: =ROUND(D275*E275,2) -> 2236696.8 | G275: =SUM($F$16:F275) -> 4.3428784e+08
A276: 261 | B276: June | C276: 2020 | D276: 647117.67 | E276: ='FORM D'!G282 -> 3.744892 | F276: =ROUNDUP(D276*E276,2) -> 2423385.8 | G276: =SUM($F$16:F276) -> 4.3671123e+08
A277: 262 | B277: July | C277: 2020 | D277: 646491.71 | E277: ='FORM D'!G283 -> 3.939529 | F277: =ROUND(D277*E277,2) -> 2546872.8 | G277: =SUM($F$16:F277) -> 4.392581e+08
A278: 263 | B278: August | C278: 2020 | D278: 661473.12 | E278: ='FORM D'!G284 -> 3.991268 | F278: =ROUND(D278*E278,2) -> 2640116.5 | G278: =SUM($F$16:F278) -> 4.4189822e+08
A279: 264 | B279: September | C279: 2020 | D279: 653254.93 | E279: ='FORM D'!G285 -> 3.966631 | F279: =ROUND(D279*E279,2) -> 2591221.3 | G279: =SUM($F$16:F279) -> 4.4448944e+08
A280: 265 | B280: October | C280: 2020 | D280: 678400.67 | E280: ='FORM D'!G286 -> 3.863152 | F280: =ROUND(D280*E280,2) -> 2620764.9 | G280: =SUM($F$16:F280) -> 4.471102e+08 | I280: Penalty Corrections - March 2021
A281: 266 | B281: November | C281: 2020 | D281: 656623.74 | E281: ='FORM D'!G287 -> 3.850834 | F281: =ROUND(D281*E281,2) -> 2528549 | G281: =SUM($F$16:F281) -> 4.4963875e+08 | I281: Original March 2021 Amount for Escalation | J281: Penalties | K281: Adjusted Amount for Escalation
A282: 267 | B282: December | C282: 2020 | D282: 693510.16 | E282: ='FORM D'!G288 -> 3.873008 | F282: =ROUND(D282*E282,2) -> 2685970.4 | G282: =SUM($F$16:F282) -> 4.5232472e+08
A283: 268 | B283: January | C283: 2021 | D283: 651715.2 | E283: ='FORM D'!G289 -> 3.934602 | F283: =ROUND(D283*E283,2) -> 2564239.9 | G283: =SUM($F$16:F283) -> 4.5488896e+08 | I283: 684003.84 | J283: -6674.16 | K283: =I283+J283 -> 677329.68
A284: 269 | B284: February | C284: 2021 | D284: 629066.58 | E284: ='FORM D'!G290 -> 4.001123 | F284: =ROUND(D284*E284,2) -> 2516972.8 | G284: =SUM($F$16:F284) -> 4.5740593e+08
A285: 270 | B285: March | C285: 2021 | D285: 677329.68 | E285: ='FORM D'!G291 -> 4.065181 | F285: =ROUND(D285*E285,2) -> 2753467.8 | G285: =SUM($F$16:F285) -> 4.601594e+08
A286: 271 | B286: April | C286: 2021 | D286: 661593.74 | E286: ='FORM D'!G292 -> 4.136631 | F286: =ROUND(D286*E286,2) -> 2736769.2 | G286: =SUM($F$16:F286) -> 4.6289617e+08
A287: 272 | B287: May | C287: 2021 | D287: 664256.87 | E287: ='FORM D'!G293 -> 4.102138 | F287: =ROUND(D287*E287,2) -> 2724873.4 | G287: =SUM($F$16:F287) -> 4.6562104e+08 | I287: Public Holiday Corrections - December 2021
A288: 273 | B288: June | C288: 2021 | D288: 648082.28 | E288: ='FORM D'!G294 -> 4.126776 | F288: =ROUND(D288*E288,2) -> 2674490.4 | G288: =SUM($F$16:F288) -> 4.6829553e+08 | I288: Original November 2021 Amount for Escalation | J288: Correction Amount | K288: Adjusted Amount for Escalation
A289: 274 | B289: July | C289: 2021 | D289: 634633.74 | E289: ='FORM D'!G295 -> 4.251699 | F289: =ROUND(D289*E289,2) -> 2698271.6 | G289: =SUM($F$16:F289) -> 4.7099381e+08
A290: 275 | B290: August | C290: 2021 | D290: 665412.64 | E290: ='FORM D'!G296 -> 4.313293 | F290: =ROUND(D290*E290,2) -> 2870119.7 | G290: =SUM($F$16:F290) -> 4.7386393e+08 | I290: 674246.78 | J290: -17606.35 | K290: 656640.43
A291: 276 | B291: September | C291: 2021 | D291: 658666.33 | E291: ='FORM D'!G297 -> 4.29851 | F291: =ROUND(D291*E291,2) -> 2831283.8 | G291: =SUM($F$16:F291) -> 4.7669521e+08
A292: 277 | B292: October | C292: 2021 | D292: 670057.38 | E292: ='FORM D'!G298 -> 4.323148 | F292: =ROUND(D292*E292,2) -> 2896757.2 | G292: =SUM($F$16:F292) -> 4.7959197e+08
A293: 278 | B293: November | C293: 2021 | D293: 656640.43 | E293: ='FORM D'!G299 -> 4.493148 | F293: =ROUND(D293*E293,2) -> 2950382.6 | G293: =SUM($F$16:F293) -> 4.8254235e+08 | I293: Penalty Corrections - March 2022
A294: 279 | B294: December | C294: 2021 | D294: 688748.9 | E294: ='FORM D'!G300 -> 4.576916 | F294: =ROUND(D294*E294,2) -> 3152345.9 | G294: =SUM($F$16:F294) -> 4.856947e+08 | I294: Original March 2022 Amount for Escalation | J294: Penalties | K294: Adjusted Amount for Escalation
A295: 280 | B295: January | C295: 2022 | D295: 665270.85 | E295: ='FORM D'!G301 -> 4.498075 | F295: =ROUND(D295*E295,2) -> 2992438.2 | G295: =SUM($F$16:F295) -> 4.8868713e+08
A296: 281 | B296: February | C296: 2022 | D296: 664132.74 | E296: ='FORM D'!G302 -> 4.589235 | F296: =ROUND(D296*E296,2) -> 3047861.2 | G296: =SUM($F$16:F296) -> 4.9173499e+08 | I296: 684003.84 | J296: -1834.47 | K296: =I296+J296 -> 682169.37
A297: 282 | B297: March | C297: 2022 | D297: 682169.37 | E297: ='FORM D'!G303 -> 4.756771 | F297: =ROUND(D297*E297,2) -> 3244923.5 | G297: =SUM($F$16:F297) -> 4.9497992e+08
A298: 283 | B298: April | C298: 2022 | D298: 654107.23 | E298: ='FORM D'!G304 -> 4.941554 | F298: =ROUND(D298*E298,2) -> 3232306.2 | G298: =SUM($F$16:F298) -> 4.9821222e+08 | I298: Penalty Corrections - March 2023
A299: 284 | B299: May | C299: 2022 | D299: 663870.5 | E299: ='FORM D'!G305 -> 5.047496 | F299: =ROUND(D299*E299,2) -> 3350883.7 | G299: =SUM($F$16:F299) -> 5.0156311e+08 | I299: Original March 2023 Amount for Escalation | J299: Penalties | K299: Adjusted Amount for Escalation
A300: 285 | B300: June | C300: 2022 | D300: 657777.63 | E300: ='FORM D'!G306 -> 5.170684 | F300: =ROUND(D300*E300,2) -> 3401160.3 | G300: =SUM($F$16:F300) -> 5.0496427e+08
A301: 286 | B301: July | C301: 2022 | D301: 678718.35 | E301: ='FORM D'!G307 -> 5.511506 | F301: =ROUND(D301*E301,2) -> 3740760.3 | G301: =SUM($F$16:F301) -> 5.0870503e+08 | I301: =D309 -> 677014.33 | J301: -5695.61 | K301: =I301+J301 -> 671318.72
A302: 287 | B302: August | C302: 2022 | D302: 683130.5 | E302: ='FORM D'!G308 -> 5.410492 | F302: =ROUND(D302*E302,2) -> 3696072.1 | G302: =SUM($F$16:F302) -> 5.124011e+08
A303: 288 | B303: September | C303: 2022 | D303: 659138.6 | E303: ='FORM D'!G309 -> 5.351361 | F303: =ROUND(D303*E303,2) -> 3527288.6 | G303: =SUM($F$16:F303) -> 5.1592839e+08
A304: 289 | B304: October | C304: 2022 | D304: 679702.8 | E304: ='FORM D'!G310 -> 5.366144 | F304: =ROUND(D304*E304,2) -> 3647383.1 | G304: =SUM($F$16:F304) -> 5.1957577e+08 | I304: In June 2023, penalty values were incorrectly added to the Code 4 penalties. This amounted to R11 303.21 and was added on Form C of this Payment Certificate. Kindly refer to the table below:
A305: 290 | B305: November | C305: 2022 | D305: 675591.86 | E305: ='FORM D'!G311 -> 5.531216 | F305: =ROUND(D305*E305,2) -> 3736844.5 | G305: =SUM($F$16:F305) -> 5.2331262e+08 | I305: Penalty Corrections - June 2023
A306: 291 | B306: December | C306: 2022 | D306: 686252.46 | E306: ='FORM D'!G312 -> 5.351361 | F306: =ROUND(D306*E306,2) -> 3672384.6 | G306: =SUM($F$16:F306) -> 5.26985e+08 | I306: Original June 2023 Amount for Escalation | J306: Penalties | K306: Adjusted Amount for Escalation
A307: 292 | B307: January | C307: 2023 | D307: 663472.56 | E307: ='FORM D'!G313 -> 5.038463 | F307: =ROUND(D307*E307,2) -> 3342882 | G307: =SUM($F$16:F307) -> 5.3032788e+08
A308: 293 | B308: February | C308: 2023 | D308: 647192.43 | E308: ='FORM D'!G314 -> 5.04339 | F308: =ROUND(D308*E308,2) -> 3264043.8 | G308: =SUM($F$16:F308) -> 5.3359193e+08 | I308: 618400.41 | J308: ='FORM B'!V297 -> 11393.21 | K308: =I308+J308 -> 629793.62
A309: 294 | B309: March | C309: 2023 | D309: 677014.33 | E309: ='FORM D'!G315 -> 5.077883 | F309: =ROUND(D309*E309,2) -> 3437799.6 | G309: =SUM($F$16:F309) -> 5.3702973e+08
A310: 295 | B310: April | C310: 2023 | D310: 686386.48 | E310: ='FORM D'!G316 -> 4.989187 | F310: =ROUND(D310*E310,2) -> 3424510.5 | G310: =SUM($F$16:F310) -> 5.4045424e+08
A311: 296 | B311: May | C311: 2023 | D311: 675481.44 | E311: ='FORM D'!G317 -> 4.920202 | F311: =ROUND(D311*E311,2) -> 3323505.1 | G311: =SUM($F$16:F311) -> 5.4377774e+08 | I311: Penalty Corrections - April 2024
A312: 297 | B312: June | C312: 2023 | D312: 629793.62 | E312: ='FORM D'!G318 -> 4.908013 | F312: =ROUND(D312*E312,2) -> 3091035.3 | G312: =SUM($F$16:F312) -> 5.4686878e+08 | I312: Original April 2024 Amount for Escalation | J312: Penalties | K312: Adjusted Amount for Escalation
A313: 298 | B313: July | C313: 2023 | D313: 678856.29 | E313: ='FORM D'!G319 -> 4.925259 | F313: =ROUND(D313*E313,2) -> 3343543 | G313: =SUM($F$16:F313) -> 5.5021232e+08
A314: 299 | B314: August | C314: 2023 | D314: 681197.98 | E314: ='FORM D'!G320 -> 5.006563 | F314: =ROUND(D314*E314,2) -> 3410460.6 | G314: =SUM($F$16:F314) -> 5.5362278e+08 | I314: 678985.46 | J314: =M345 -> 2363.9 | K314: =I314+J314 -> 681349.36
A315: 300 | B315: September | C315: 2023 | D315: 696255.21 | E315: ='FORM D'!G321 -> 5.326853 | F315: =ROUND(D315*E315,2) -> 3708849.1 | G315: =SUM($F$16:F315) -> 5.5733163e+08
A316: 301 | B316: October | C316: 2023 | D316: 680554.6 | E316: ='FORM D'!G322 -> 5.551056 | F316: =ROUND(D316*E316,2) -> 3777796.7 | G316: =SUM($F$16:F316) -> 5.6110943e+08
A317: 302 | B317: November | C317: 2023 | D317: 674627.51 | E317: ='FORM D'!G323 -> 5.454969 | F317: =ROUND(D317*E317,2) -> 3680072.1 | G317: =SUM($F$16:F317) -> 5.647895e+08
A318: 303 | B318: December | C318: 2023 | D318: 695551.71 | E318: ='FORM D'!G324 -> 5.181491 | F318: =ROUND(D318*E318,2) -> 3603994.9 | G318: =SUM($F$16:F318) -> 5.6839349e+08
A319: 304 | B319: January | C319: 2024 | D319: 682897.33 | E319: ='FORM D'!G325 -> 5.041056 | F319: =ROUND(D319*E319,2) -> 3442523.7 | G319: =SUM($F$16:F319) -> 5.7183602e+08
A320: 305 | B320: February | C320: 2024 | D320: 688105.93 | E320: ='FORM D'!G326 -> 5.12236 | F320: =ROUND(D320*E320,2) -> 3524726.3 | G320: =SUM($F$16:F320) -> 5.7536074e+08
A321: 306 | B321: March | C321: 2024 | D321: 676621.56 | E321: ='FORM D'!G327 -> 5.25294 | F321: =ROUND(D321*E321,2) -> 3554252.5 | G321: =SUM($F$16:F321) -> 5.78915e+08
A322: 307 | B322: April | C322: 2024 | D322: 681349.36 | E322: ='FORM D'!G328 -> 5.248013 | F322: =ROUND(D322*E322,2) -> 3575730.3 | G322: =SUM($F$16:F322) -> 5.8249073e+08
A323: 308 | B323: May | C323: 2024 | D323: 664155.11 | E323: ='FORM D'!G329 -> 5.211056 | F323: =ROUND(D323*E323,2) -> 3460949.5 | G323: =SUM($F$16:F323) -> 5.8595168e+08
A324: 309 | B324: June | C324: 2024 | D324: 678592.78 | E324: ='FORM D'!G330 -> 5.080476 | F324: =ROUND(D324*E324,2) -> 3447574.3 | G324: =SUM($F$16:F324) -> 5.8939925e+08
A325: 310 | B325: July | C325: 2024 | D325: 647706.56 | E325: ='FORM D'!G331 -> 5.150224 | F325: =ROUND(D325*E325,2) -> 3335833.9 | G325: =SUM($F$16:F325) -> 5.9273508e+08
A326: 311 | B326: August | C326: 2024 | D326: 645677.29 | E326: ='FORM D'!G332 -> 5.125586 | F326: =ROUND(D326*E326,2) -> 3309474.5 | G326: =SUM($F$16:F326) -> 5.9604456e+08
... A334: 319 | B334: April | C334: 2025 | D334: 645354.33 | E334: ='FORM D'!G340 -> 4.982687 | F334: =ROUND(D334*E334,2) -> 3215598.6 | G334: =SUM($F$16:F334) -> 6.2230576e+08
A335: 320 | B335: May | C335: 2025 | D335: ='FORM E'!$H$39 -> 676830.65 | E335: ='FORM D'!G341 -> 4.982687 | F335: =ROUND(D335*E335,2) -> 3372435.3 | G335: =SUM($F$16:F335) -> 6.256782e+08
F337: TOTAL | G337: =SUM(F16:F336) -> 6.256782e+08
H338: 45383 | I338: 1B2 | J338: JOZINI | K338: MKUZE | L338: INGWAVUMA | M338: 298.55 | N338: DOUBLE | O338: TESS
H339: 45413 | I339: 1B2 | J339: JOZINI | K339: MKUZE | L339: INGWAVUMA | M339: 298.55 | N339: DOUBLE | O339: TESS
H340: 45444 | I340: 1A1 | J340: JOZINI | K340: MKUZE | L340: INGWAVUMA | M340: 286.3 | N340: DOUBLE | O340: TESS
H341: 45474 | I341: 1B2 | J341: JOZINI | K341: MKUZE | L341: INGWAVUMA | M341: 298.55 | N341: DOUBLE | O341: TESS
M343: =SUM(M338:M342) -> 1181.95
L344: DOUBLE | M344: =M343 -> 1181.95
M345: =SUM(M343:M344) -> 2363.9

Sheet FORM D
D1: FORM D
A3: PUBLIC TRANSPORT : | C3: ='FORM A'!C3 -> PROVISION OF PUBLIC PASSENGER TRANSPORT MKUZE AND SURROUNDING
A5: ='FORM A'!A6 -> CONTRACT : ZNT 1129 | E5: OPERATOR : | F5: ='FORM A'!F6 -> Ripple Effect 40 (Pty) Ltd
A7: PAYMENT CERTIFICATE NO : | C7: ='FORM A'!C8 -> 320 | E7: FOR MONTH : | F7: ='FORM C'!F7 -> 45778
A9: ESCALATION FORMULA (REFER GCC CLAUSE 37)
A10: INDICES WEIGHTED AVERAGE : | E10: BASE MONTH = | F10: 36039
A12: f = (1-x) ((a x (Lt/Lo + b x (Bt/Bo) + (c x Ft/ Fo) - 1)
A14: with
A15: x = | B15: 0.15 | D15: Lo | E15: 19 | F15: SEIFSA
A16: a = | B16: 0.35
A17: b = | B17: 0.45 | D17: Bo | E17: 49.4 | F17: Bus & Truck Index (PPI Report)
A18: c = | B18: 0.2
D19: Fo | E19: 6.9 | F19: Fuel Index (PPI Report)
A21: CERT NO. | B21: MONTH | C21: YEAR | D21: Lt | E21: Bt | F21: Ft | G21: f + 1
A22: 1 | B22: November | C22: 1998 | D22: 19.528979 | E22: 50.9 | F22: 7.1088644 | G22: =((1-$B$15)*(($B$16*D22/$E$15)+($B$17*E22/$E$17)+($B$18*F22/$E$19)-1))+1 -> 1.025043
A23: =A22+1 -> 2 | B23: December | C23: 1998 | D23: 19.528979 | E23: 50.9 | F23: 6.8348919 | G23: =((1-$B$15)*(($B$16*D23/$E$15)+($B$17*E23/$E$17)+($B$18*F23/$E$19)-1))+1 -> 1.018293
A24: =A23+1 -> 3 | B24: January | C24: 1999 | D24: 19.528979 | E24: 51.5 | F24: 6.6618567 | G24: =((1-$B$15)*(($B$16*D24/$E$15)+($B$17*E24/$E$17)+($B$18*F24/$E$19)-1))+1 -> 1.0186755
A25: =A24+1 -> 4 | B25: February | C25: 1999 | D25: 19.528979 | E25: 51.6 | F25: 7.0944448 | G25: =((1-$B$15)*(($B$16*D25/$E$15)+($B$17*E25/$E$17)+($B$18*F25/$E$19)-1))+1 -> 1.0301078
A26: =A25+1 -> 5 | B26: March | C26: 1999 | D26: 19.528979 | E26: 51.6 | F26: 7.0656056 | G26: =((1-$B$15)*(($B$16*D26/$E$15)+($B$17*E26/$E$17)+($B$18*F26/$E$19)-1))+1 -> 1.0293972
A27: =A26+1 -> 6 | B27: April | C27: 1999 | D27: 19.528979 | E27: 53.5 | F27: 7.2242212 | G27: =((1-$B$15)*(($B$16*D27/$E$15)+($B$17*E27/$E$17)+($B$18*F27/$E$19)-1))+1 -> 1.0480167
A28: =A27+1 -> 7 | B28: May | C28: 1999 | D28: 19.528979 | E28: 53.6 | F28: 7.7865857 | G28: =((1-$B$15)*(($B$16*D28/$E$15)+($B$17*E28/$E$17)+($B$18*F28/$E$19)-1))+1 -> 1.0626464
A29: =A28+1 -> 8 | B29: June | C29: 1999 | D29: 19.528979 | E29: 53.6 | F29: 8.0749778 | G29: =((1-$B$15)*(($B$16*D29/$E$15)+($B$17*E29/$E$17)+($B$18*F29/$E$19)-1))+1 -> 1.0697517
A30: =A29+1 -> 9 | B30: July | C30: 1999 | D30: 20.742849 | E30: 53.6 | F30: 8.2624326 | G30: =((1-$B$15)*(($B$16*D30/$E$15)+($B$17*E30/$E$17)+($B$18*F30/$E$19)-1))+1 -> 1.0933768
A31: =A30+1 -> 10 | B31: August | C31: 1999 | D31: 20.742849 | E31: 54.2 | F31: 8.7382796 | G31: =((1-$B$15)*(($B$16*D31/$E$15)+($B$17*E31/$E$17)+($B$18*F31/$E$19)-1))+1 -> 1.1097463
A32: =A31+1 -> 11 | B32: September | C32: 1999 | D32: 20.742849 | E32: 54.2 | F32: 9.3006441 | G32: =((1-$B$15)*(($B$16*D32/$E$15)+($B$17*E32/$E$17)+($B$18*F32/$E$19)-1))+1 -> 1.1236016
A33: =A32+1 -> 12 | B33: October | C33: 1999 | D33: 20.742849 | E33: 54.2 | F33: 9.7909106 | G33: =((1-$B$15)*(($B$16*D33/$E$15)+($B$17*E33/$E$17)+($B$18*F33/$E$19)-1))+1 -> 1.1356807
A34: =A33+1 -> 13 | B34: November | C34: 1999 | D34: 20.742849 | E34: 54.2 | F34: 10.151401 | G34: =((1-$B$15)*(($B$16*D34/$E$15)+($B$17*E34/$E$17)+($B$18*F34/$E$19)-1))+1 -> 1.1445623
... A280: =A279+1 -> 259 | B280: April | C280: 2020 | D280: 85.194906 | E280: 129.4 | F280: 57.5 | G280: =((1-$B$15)*(($B$16*D280/$E$15)+($B$17*E280/$E$17)+($B$18*F280/$E$19)-1))+1 -> 3.9025727
A281: =A280+1 -> 260 | B281: May | C281: 2020 | D281: 85.194906 | E281: 129.4 | F281: 50.2 | G281: =ROUND(((1-$B$15)*(($B$16*D281/$E$15)+($B$17*E281/$E$17)+($B$18*F281/$E$19)-1))+1,6) -> 3.722718
A282: 261 | B282: June | C282: 2020 | D282: 85.194906 | E282: 129.4 | F282: 51.1 | G282: =ROUND(((1-$B$15)*(($B$16*D282/$E$15)+($B$17*E282/$E$17)+($B$18*F282/$E$19)-1))+1,6) -> 3.744892
A283: 262 | B283: July | C283: 2020 | D283: 85.194906 | E283: 129.4 | F283: 59 | G283: =ROUND(((1-$B$15)*(($B$16*D283/$E$15)+($B$17*E283/$E$17)+($B$18*F283/$E$19)-1))+1,6) -> 3.939529
A284: 263 | B284: August | C284: 2020 | D284: 85.194906 | E284: 129.4 | F284: 61.1 | G284: =ROUND(((1-$B$15)*(($B$16*D284/$E$15)+($B$17*E284/$E$17)+($B$18*F284/$E$19)-1))+1,6) -> 3.991268
A285: 264 | B285: September | C285: 2020 | D285: 85.194906 | E285: 129.4 | F285: 60.1 | G285: =ROUND(((1-$B$15)*(($B$16*D285/$E$15)+($B$17*E285/$E$17)+($B$18*F285/$E$19)-1))+1,6) -> 3.966631
A286: 265 | B286: October | C286: 2020 | D286: 85.194906 | E286: 129.4 | F286: 55.9 | G286: =ROUND(((1-$B$15)*(($B$16*D286/$E$15)+($B$17*E286/$E$17)+($B$18*F286/$E$19)-1))+1,6) -> 3.863152
A287: 266 | B287: November | C287: 2020 | D287: 85.194906 | E287: 129.4 | F287: 55.4 | G287: =ROUND(((1-$B$15)*(($B$16*D287/$E$15)+($B$17*E287/$E$17)+($B$18*F287/$E$19)-1))+1,6) -> 3.850834
A288: 267 | B288: December | C288: 2020 | D288: 85.194906 | E288: 129.4 | F288: 56.3 | G288: =ROUND(((1-$B$15)*(($B$16*D288/$E$15)+($B$17*E288/$E$17)+($B$18*F288/$E$19)-1))+1,6) -> 3.873008
A289: 268 | B289: January | C289: 2021 | D289: 85.194906 | E289: 129.4 | F289: 58.8 | G289: =ROUND(((1-$B$15)*(($B$16*D289/$E$15)+($B$17*E289/$E$17)+($B$18*F289/$E$19)-1))+1,6) -> 3.934602
A290: 269 | B290: February | C290: 2021 | D290: 85.194906 | E290: 129.4 | F290: 61.5 | G290: =ROUND(((1-$B$15)*(($B$16*D290/$E$15)+($B$17*E290/$E$17)+($B$18*F290/$E$19)-1))+1,6) -> 4.001123
A291: 270 | B291: March | C291: 2021 | D291: 85.194906 | E291: 129.4 | F291: 64.1 | G291: =ROUND(((1-$B$15)*(($B$16*D291/$E$15)+($B$17*E291/$E$17)+($B$18*F291/$E$19)-1))+1,6) -> 4.065181
A292: 271 | B292: April | C292: 2021 | D292: 85.194906 | E292: 129.4 | F292: 67 | G292: =ROUND(((1-$B$15)*(($B$16*D292/$E$15)+($B$17*E292/$E$17)+($B$18*F292/$E$19)-1))+1,6) -> 4.136631
A293: 272 | B293: May | C293: 2021 | D293: 85.194906 | E293: 129.4 | F293: 65.6 | G293: =ROUND(((1-$B$15)*(($B$16*D293/$E$15)+($B$17*E293/$E$17)+($B$18*F293/$E$19)-1))+1,6) -> 4.102138
... A341: 320 | B341: May | C341: 2025 | D341: 106.5 | E341: 129.4 | F341: 87.8 | G341: =ROUND(((1-$B$15)*(($B$16*D341/$E$15)+($B$17*E341/$E$17)+($B$18*F341/$E$19)-1))+1,6) -> 4.982687
A344: * | B344: Left justified factors are provisional figures, pending the availability of official indices.

Sheet FORM E
A1: FORM E
B2: REQUEST FOR MONTHLY PAYMENT
B4: The Representative
B6: For Attention : | C6: Petrus Ackerman
B8: PUBLIC TRANSPORT : | D8: ='FORM A'!C3 -> PROVISION OF PUBLIC PASSENGER TRANSPORT MKUZE AND SURROUNDING
B10: ='FORM A'!A6 -> CONTRACT : ZNT 1129 | E10: OPERATOR : | F10: ='FORM A'!F6 -> Ripple Effect 40 (Pty) Ltd
B12: PAYMENT CERTIFICATE NO.: | D12: =+'FORM A'!C8 -> 320 | E12: FOR MONTH : | F12: ='FORM A'!F8 -> 45778
K14: FORM 9 - SCHEDULE OF QUANTITIES
B15: Enclosed Schedule Form F from 1 to 31 May 2025 for the above contract
B17: Total scheduled revenue kms = | D17: ='FORM F1 SUB - STD BUS'!M58 -> 82763.4 | M17: Rates | N17: Months | O17: Kms | P17: Rand Value
B19: The total non-escalated amount claimed for this month is made up as follows : | J19: 1 | K19: 20301 | L19: 4.58
J20: 2 | K20: 19300 | L20: 4.82
A21: OPERATED KM: | J21: 3 | K21: 18300 | L21: 5.08
J22: 4 | K22: 17300 | L22: 5.38
B23: A. Bus | C23: ='FORM F1 SUB - STD BUS'!N58 -> 82529.4 | D23: Revenue kms at contract rate | F23: =IF(D17>95000,7.11,IF(D17>90000,7.32,IF(D17>85000,7.59,IF(D17>80000,8.21,IF(D17>75000,8.75,IF(D17>70000,9.35)))))) -> 8.21 | G23: = | H23: =ROUND(C23*F23,2) -> 677566.37 | J23: 5 | K23: 0 | L23: 5.38
O24: TOTAL | P24: =SUM(#REF!) -> #REF!
D25: SUBTOTAL | H25: =SUM(H23:H23) -> 677566.37 | J25: =F23*1.5 -> 12.315
A27: STANDING KM:
B29: A. Bus | C29: ='FORM F1 SUB - STD BUS'!Z58 -> 234 | D29: kms at contract rate | F29: =ROUND(F23*0.6,2) -> 4.93 | G29: = | H29: =ROUND(C29*F29,2) -> 1153.62 | J29: =F23*0.6 -> 4.926
B32: Less non-refundable penalties imposed for not operating in accordance with
B33: the contract specifications :
B35: GCC Clause 21 and SCC Clause 5, from FORM G | G35: = | H35: ='FORM G2'!I35 -> 1889.34
D39: TOTAL carried to Form C (Col 4) for escalation | H39: =SUM(H25:H29)-H35 -> 676830.65
B43: Signed on behalf of Operator: | D43: ='FORM A'!F6 -> Ripple Effect 40 (Pty) Ltd
B47: Signature | G47: Date:
B51: Approval of claim by Representative
B54: Signature | F54: Date

Sheet FORM H
A1: FORM H
A3: PUBLIC TRANSPORT : | C3: ='FORM A'!C3 -> PROVISION OF PUBLIC PASSENGER TRANSPORT MKUZE AND SURROUNDING
A5: ='FORM A'!A6 -> CONTRACT : ZNT 1129 | F5: OPERATOR : | G5: ='FORM A'!F6 -> Ripple Effect 40 (Pty) Ltd
A7: PAYMENT CERTIFICATE NO.: | D7: ='FORM A'!C8 -> 320 | F7: FOR MONTH : | G7: ='FORM A'!F8 -> 45778
A9: BUDGET CONTRACT EXPENDITURE FORM
F10: FINANCIAL YEAR:
F11: SUBSIDY ALLOCATION:
D14: Kilometres | F14: Monthly Subsidy
A16: Certificate | B16: Month | C16: Year | D16: Scheduled | E16: Operated | F16: Budgeted | G16: Monies | H16: Monies | I16: Balance | K16: PTOG
A17: No. | G17: Claimed | H17: Paid | K17: Refund Claimed
A19: 1 | B19: 2 | C19: 3 | D19: 4 | E19: 5 | F19: 6 | G19: 7 | H19: 8 | I19: 9
A20: 22 | B20: August | C20: 2000 | G20: ='FORM B'!H38 -> 782646.53
A21: =A20+1 -> 23 | B21: September | C21: 2000 | G21: ='FORM B'!H39 -> 888930.16
A22: =A21+1 -> 24 | B22: October | C22: 2000 | G22: ='FORM B'!H40 -> 902304.65
A23: =A22+1 -> 25 | B23: November | C23: 2000 | G23: ='FORM B'!H41 -> 795334.02
A24: =A23+1 -> 26 | B24: December | C24: 2000 | G24: ='FORM B'!H42 -> 783205.09
A25: =A24+1 -> 27 | B25: January | C25: 2001 | G25: ='FORM B'!H43 -> 470298.4
A26: =A25+1 -> 28 | B26: February | C26: 2001 | G26: ='FORM B'!H44 -> 319622.65
A27: =A26+1 -> 29 | B27: March | C27: 2001 | G27: ='FORM B'!H45 -> 648587.46
A28: =A27+1 -> 30 | B28: April | C28: 2001 | G28: ='FORM B'!H46 -> 657436.78
A29: =A28+1 -> 31 | B29: May | C29: 2001 | G29: ='FORM B'!H47 -> 657436.78
A30: 32 | B30: May | C30: 2001 | G30: ='FORM B'!H48 -> 112530.6
A31: =A30+1 -> 33 | B31: June | C31: 2001 | G31: ='FORM B'!H49 -> 564446.96
A32: =A31+1 -> 34 | B32: July | C32: 2001 | G32: ='FORM B'!H50 -> 704751.57
A33: =A32+1 -> 35 | B33: August | C33: 2001 | G33: ='FORM B'!H51 -> 820266.15
A34: =A33+1 -> 36 | B34: September | C34: 2001 | G34: ='FORM B'!H52 -> -58633.52
A35: =A34+1 -> 37 | B35: October | C35: 2001 | G35: ='FORM B'!H53 -> 4211.92
A36: =A35+1 -> 38 | B36: November | C36: 2001 | G36: ='FORM B'!H54 -> 354016.29
A37: =A36+1 -> 39 | B37: December | C37: 2002 | G37: ='FORM B'!H55 -> 923872.94
A38: =A37+1 -> 40 | B38: January | C38: 2002 | G38: ='FORM B'!H56 -> 950628.74
A39: =A38+1 -> 41 | B39: February | C39: 2002 | G39: ='FORM B'!H57 -> 991401.45
A40: =A39+1 -> 42 | B40: March | C40: 2002 | G40: ='FORM B'!H58 -> 997903.87
A41: =A40+1 -> 43 | B41: April | C41: 2002 | G41: ='FORM B'!H59 -> 965310.04
A42: =A41+1 -> 44 | B42: May | C42: 2002 | G42: ='FORM B'!H60 -> 1104643.1
... A64: =A63+1 -> 66 | B64: March | C64: 2004 | G64: ='FORM B'!H82 -> 1009176.1
A65: =A64+1 -> 67 | B65: April | C65: 2004 | D65: 82921 | E65: 82761.203 | G65: ='FORM B'!H83 -> 1178064.2
A66: =A65+1 -> 68 | B66: May | C66: 2004 | D66: 80209.102 | E66: 79858.5 | G66: ='FORM B'!H84 -> 1029890.6
A67: =A66+1 -> 69 | B67: June | C67: 2004 | D67: 84907.898 | E67: 84739.898 | G67: ='FORM B'!H85 -> 991602.66
A68: =A67+1 -> 70 | B68: July | C68: 2004 | D68: 81169 | E68: 81128 | G68: ='FORM B'!H86 -> 1124215.7
A69: =A68+1 -> 71 | B69: August | C69: 2004 | D69: 80366.703 | E69: 80296.398 | G69: ='FORM B'!H87 -> 1035409.2
A70: =A69+1 -> 72 | B70: September | C70: 2004 | D70: 82763.398 | E70: 82763.398 | G70: ='FORM B'!H88 -> 1084676.7
A71: =A70+1 -> 73 | B71: October | C71: 2004 | D71: 82353.602 | E71: 81481.898 | G71: ='FORM B'!H89 -> 1143259.6
A72: =A71+1 -> 74 | B72: November | C72: 2004 | D72: 79259.398 | E72: 78307.602 | G72: ='FORM B'!H90 -> 1134642.8
A73: =A72+1 -> 75 | B73: December | C73: 2005 | D73: 81169 | E73: 81169 | G73: ='FORM B'!H91 -> 1185206.4
A74: =A73+1 -> 76 | B74: January | C74: 2005 | D74: 76144.797 | E74: 76144.797 | G74: ='FORM B'!H92 -> 1105175.3
A75: =A74+1 -> 77 | B75: February | C75: 2005 | D75: 79182.102 | E75: 79076 | G75: ='FORM B'!H93 -> 1048366
A76: =A75+1 -> 78 | B76: March | C76: 2005 | D76: 79659 | E76: 79659 | G76: ='FORM B'!H94 -> 1348637
... A259: =A258+1 -> 261 | B259: June | C259: 2020 | D259: 80209.1 | E259: 77619.4 | G259: ='FORM B'!H277 -> 2366868.4
A260: 262 | B260: July | C260: 2020 | D260: 85300.4 | E260: 85300.4 | G260: ='FORM B'!H278 -> 2213598
A261: 263 | B261: August | C261: 2020 | D261: 80776.5 | E261: 80776.5 | G261: ='FORM B'!H279 -> 2737288.4
A262: 264 | B262: September | C262: 2020 | D262: 80209.1 | E262: 79097.5 | G262: ='FORM B'!H280 -> 2645362.2
A263: 265 | B263: October | C263: 2020 | D263: 84907.9 | E263: 79387.6 | G263: ='FORM B'!H281 -> 2680357.9
A264: 266 | B264: November | C264: 2020 | D264: 80209.1 | E264: 80209.1 | G264: ='FORM B'!H282 -> 2469156.5
A265: 267 | B265: December | C265: 2020 | D265: 79574.6 | E265: 79340.6 | G265: ='FORM B'!H283 -> 2666220.5
A266: 268 | B266: January | C266: 2021 | D266: 80776.5 | E266: 77904.1 | G266: ='FORM B'!H284 -> 2543519.3
A267: 269 | B267: February | C267: 2021 | D267: 76144.8 | E267: 65887.7 | G267: ='FORM B'!H285 -> 2481269.4
A268: 270 | B268: March | C268: 2021 | D268: 83313.5 | E268: 83313.5 | G268: ='FORM B'!H286 -> 2695839
A269: 271 | B269: April | C269: 2021 | D269: 75920.1 | E269: 75491.1 | G269: ='FORM B'!H287 -> 2796796.5
A270: 272 | B270: May | C270: 2021 | D270: 81169 | E270: 81169 | G270: ='FORM B'!H288 -> 2800161.9
A271: 273 | B271: June | C271: 2021 | D271: 80209.1 | E271: 77725.9 | G271: ='FORM B'!H289 -> 2639490.4
... A317: 319 | B317: April | C317: 2025 | D317: 76077.7 | E317: 71125.4 | G317: ='FORM B'!H335 -> 191289.43
A318: 320 | B318: May | C318: 2025 | D318: ='FORM F1 SUB - STD BUS'!$M$58 -> 82763.4 | E318: ='FORM F1 SUB - STD BUS'!$N$58 -> 82529.4 | G318: ='FORM B'!H336 -> 3308835
B321: TOTAL | D321: =SUM(D20:D319) -> 20482718 | E321: =SUM(E20:E319) -> 19999102 | F321: =SUM(F20:F320) -> 0 | G321: =SUM(G20:G320) -> 6.0230159e+08 | H321: =SUM(H20:H320) -> 0
F323: Estimated total for the financial year | H323: =SUM(H20:H319) -> 0
B325: NOTE : | C325: Estimate will be updated and amended monthly.

Sheet FORM F1 SUB - STD BUS
B1: FORM F1 - STANDARD BUS
B3: PUBLIC TRANSPORT : | E3: ='FORM A'!C3 -> PROVISION OF PUBLIC PASSENGER TRANSPORT MKUZE AND SURROUNDING
B5: ='FORM B'!A5 -> CONTRACT : ZNT 1129 | M5: OPERATOR : | O5: ='FORM A'!F6 -> Ripple Effect 40 (Pty) Ltd
B7: CERTIFICATE NO.: | E7: ='FORM A'!C8 -> 320 | M7: FOR MONTH : | O7: ='FORM A'!F8 -> 45778
B9: OPERATIONAL STATISTICS: SUBSIDISED SERVICES
D12: ROUTE | F12: TRIPS | L12: Route | M12: KILOMETRES | O12: PASSENGERS | S12: PASSENGER REVENUE | Y12: STANDING
L13: Length | R13: Avg | V13: Avg | W13: Avg | X13: Avg
B14: No | C14: F/R | D14: From | E14: To | F14: Scheduled | G14: DNOs | H14: Late | I14: Break | J14: Non Com | K14: Operated | M14: Scheduled | N14: Operated | O14: Cash | P14: Season | Q14: Total | R14: pass/trip | S14: Cash | T14: Season | U14: Total | V14: rev/trip | W14: rev/rev km | X14: rev/pass | Y14: Trips | Z14: Kilometes
F15: ` | H15: > 30 min. | I15: Down | J15: CRW | M15: (5x11) | N15: (10x11) | Q15: (14+15) | R15: (14/10) | U15: (18+19) | V15: (20/10) | W15: (20/13) | X15: (20/16) | Z15: (24x11)
B16: 1 | C16: =B16+1 -> 2 | D16: =C16+1 -> 3 | E16: =D16+1 -> 4 | F16: =E16+1 -> 5 | G16: =F16+1 -> 6 | H16: =G16+1 -> 7 | I16: =H16+1 -> 8 | J16: =I16+1 -> 9 | ... Z16: =Y16+1 -> 25
A17: =CONCATENATE(B17,C17) -> 10F | B17: 10 | C17: F | D17: BIVA TERMINUS | E17: PONGOLA TERMINUS | F17: =VLOOKUP(A17,'FORM I1 SUB STD NORMAL'!$A$16:$O$55,15,FALSE) -> 26 | K17: =F17-G17-H17-I17-J17-Y17 -> 26 | L17: 101.5 | M17: =F17*L17 -> 2639 | N17: =K17*L17 -> 2639 | O17: 1550 | Q17: =O17+P17 -> 1550 | R17: =Q17/K17 -> 59.615385 | S17: 60120 | U17: =SUM(S17:T17) -> 60120 | V17: =U17/K17 -> 2312.3077 | W17: =U17/N17 -> 22.781357 | X17: =IF(Q17>0,U17/Q17,0) -> 38.787097 | Z17: =SUM(Y17*L17) -> 0 | AA17: =A17 -> 10F | AB17: =IFERROR(VLOOKUP(A17,[1]Sheet7!$A$4:$B$30,2,FALSE),0) -> 0 | AC17: =Y17+AB17 -> 0
A18: =CONCATENATE(B18,C18) -> 10R | B18: 10 | C18: R | D18: PONGOLA TERMINUS | E18: BIVA TERMINUS | F18: =VLOOKUP(A18,'FORM I1 SUB STD NORMAL'!$A$16:$O$55,15,FALSE) -> 26 | K18: =F18-G18-H18-I18-J18-Y18 -> 26 | L18: 101.5 | M18: =F18*L18 -> 2639 | N18: =K18*L18 -> 2639 | O18: 1593 | Q18: =O18+P18 -> 1593 | R18: =Q18/K18 -> 61.269231 | S18: 66107 | U18: =SUM(S18:T18) -> 66107 | V18: =U18/K18 -> 2542.5769 | W18: =U18/N18 -> 25.050019 | X18: =IF(Q18>0,U18/Q18,0) -> 41.498431 | Z18: =SUM(Y18*L18) -> 0 | AA18: =A18 -> 10R | AB18: =IFERROR(VLOOKUP(A18,[1]Sheet7!$A$4:$B$30,2,FALSE),0) -> 1 | AC18: =Y18+AB18 -> 1
A19: =CONCATENATE(B19,C19) -> 1A.3F | B19: 1A.3 | C19: F | D19: INGWAVUMA | E19: MKUZE | F19: =VLOOKUP(A19,'FORM I1 SUB STD NORMAL'!$A$16:$O$55,15,FALSE) -> 5 | K19: =F19-G19-H19-I19-J19-Y19 -> 5 | L19: 73.8 | M19: =F19*L19 -> 369 | N19: =K19*L19 -> 369 | O19: 519 | Q19: =O19+P19 -> 519 | R19: =Q19/K19 -> 103.8 | S19: 11366 | U19: =SUM(S19:T19) -> 11366 | V19: =U19/K19 -> 2273.2 | W19: =U19/N19 -> 30.802168 | X19: =IF(Q19>0,U19/Q19,0) -> 21.899807 | Z19: =SUM(Y19*L19) -> 0 | AA19: =A19 -> 1A.3F | AB19: =IFERROR(VLOOKUP(A19,[1]Sheet7!$A$4:$B$30,2,FALSE),0) -> 0 | AC19: =Y19+AB19 -> 0
A20: =CONCATENATE(B20,C20) -> 1A.3R | B20: 1A.3 | C20: R | D20: MKUZE | E20: INGWAVUMA | F20: =VLOOKUP(A20,'FORM I1 SUB STD NORMAL'!$A$16:$O$55,15,FALSE) -> 5 | K20: =F20-G20-H20-I20-J20-Y20 -> 5 | L20: 73.8 | M20: =F20*L20 -> 369 | N20: =K20*L20 -> 369 | O20: 346 | Q20: =O20+P20 -> 346 | R20: =Q20/K20 -> 69.2 | S20: 6357 | U20: =SUM(S20:T20) -> 6357 | V20: =U20/K20 -> 1271.4 | W20: =U20/N20 -> 17.227642 | X20: =IF(Q20>0,U20/Q20,0) -> 18.372832 | Z20: =SUM(Y20*L20) -> 0 | AA20: =A20 -> 1A.3R | AB20: =IFERROR(VLOOKUP(A20,[1]Sheet7!$A$4:$B$30,2,FALSE),0) -> 0 | AC20: =Y20+AB20 -> 0
A21: =CONCATENATE(B21,C21) -> 1A1F | B21: 1A1 | C21: F | D21: INGWAVUMA | E21: MKUZE | F21: =VLOOKUP(A21,'FORM I1 SUB STD NORMAL'!$A$16:$O$55,15,FALSE) -> 26 | K21: =F21-G21-H21-I21-J21-Y21 -> 26 | L21: 81.8 | M21: =F21*L21 -> 2126.8 | N21: =K21*L21 -> 2126.8 | O21: 1858 | Q21: =O21+P21 -> 1858 | R21: =Q21/K21 -> 71.461538 | S21: 34423.5 | U21: =SUM(S21:T21) -> 34423.5 | V21: =U21/K21 -> 1323.9808 | W21: =U21/N21 -> 16.185584 | X21: =IF(Q21>0,U21/Q21,0) -> 18.52718 | Z21: =SUM(Y21*L21) -> 0 | AA21: =A21 -> 1A1F | AB21: =IFERROR(VLOOKUP(A21,[1]Sheet7!$A$4:$B$30,2,FALSE),0) -> 1 | AC21: =Y21+AB21 -> 1
A22: =CONCATENATE(B22,C22) -> 1A1R | B22: 1A1 | C22: R | D22: MKUZE | E22: INGWAVUMA | F22: =VLOOKUP(A22,'FORM I1 SUB STD NORMAL'!$A$16:$O$55,15,FALSE) -> 26 | K22: =F22-G22-H22-I22-J22-Y22 -> 26 | L22: 90 | M22: =F22*L22 -> 2340 | N22: =K22*L22 -> 2340 | O22: 1796 | Q22: =O22+P22 -> 1796 | R22: =Q22/K22 -> 69.076923 | S22: 33554 | U22: =SUM(S22:T22) -> 33554 | V22: =U22/K22 -> 1290.5385 | W22: =U22/N22 -> 14.339316 | X22: =IF(Q22>0,U22/Q22,0) -> 18.682628 | Z22: =SUM(Y22*L22) -> 0 | AA22: =A22 -> 1A1R | AB22: =IFERROR(VLOOKUP(A22,[1]Sheet7!$A$4:$B$30,2,FALSE),0) -> 1 | AC22: =Y22+AB22 -> 1
A23: =CONCATENATE(B23,C23) -> 1A4F | B23: 1A4 | C23: F | D23: MAVELA | E23: MKUZE | F23: =VLOOKUP(A23,'FORM I1 SUB STD NORMAL'!$A$16:$O$55,15,FALSE) -> 26 | K23: =F23-G23-H23-I23-J23-Y23 -> 26 | L23: 35.8 | M23: =F23*L23 -> 930.8 | N23: =K23*L23 -> 930.8 | O23: 1202 | Q23: =O23+P23 -> 1202 | R23: =Q23/K23 -> 46.230769 | S23: 15116 | U23: =SUM(S23:T23) -> 15116 | V23: =U23/K23 -> 581.38462 | W23: =U23/N23 -> 16.239794 | X23: =IF(Q23>0,U23/Q23,0) -> 12.575707 | Z23: =SUM(Y23*L23) -> 0 | AA23: =A23 -> 1A4F | AB23: =IFERROR(VLOOKUP(A23,[1]Sheet7!$A$4:$B$30,2,FALSE),0) -> 1 | AC23: =Y23+AB23 -> 1
A24: =CONCATENATE(B24,C24) -> 1A4R | B24: 1A4 | C24: R | D24: MKUZE | E24: MAVELA | F24: =VLOOKUP(A24,'FORM I1 SUB STD NORMAL'!$A$16:$O$55,15,FALSE) -> 26 | K24: =F24-G24-H24-I24-J24-Y24 -> 26 | L24: 35.8 | M24: =F24*L24 -> 930.8 | N24: =K24*L24 -> 930.8 | O24: 1202 | Q24: =O24+P24 -> 1202 | R24: =Q24/K24 -> 46.230769 | S24: 14189.5 | U24: =SUM(S24:T24) -> 14189.5 | V24: =U24/K24 -> 545.75 | W24: =U24/N24 -> 15.244413 | X24: =IF(Q24>0,U24/Q24,0) -> 11.804908 | Z24: =SUM(Y24*L24) -> 0 | AA24: =A24 -> 1A4R | AB24: =IFERROR(VLOOKUP(A24,[1]Sheet7!$A$4:$B$30,2,FALSE),0) -> 1 | AC24: =Y24+AB24 -> 1
A25: =CONCATENATE(B25,C25) -> 1B.1F | B25: 1B.1 | C25: F | D25: INGWAVUMA | E25: MKUZE | F25: =VLOOKUP(A25,'FORM I1 SUB STD NORMAL'!$A$16:$O$55,15,FALSE) -> 31 | K25: =F25-G25-H25-I25-J25-Y25 -> 31 | L25: 90 | M25: =F25*L25 -> 2790 | N25: =K25*L25 -> 2790 | O25: 1663 | Q25: =O25+P25 -> 1663 | R25: =Q25/K25 -> 53.645161 | S25: 28845.5 | U25: =SUM(S25:T25) -> 28845.5 | V25: =U25/K25 -> 930.5 | W25: =U25/N25 -> 10.338889 | X25: =IF(Q25>0,U25/Q25,0) -> 17.34546 | Z25: =SUM(Y25*L25) -> 0 | AA25: =A25 -> 1B.1F | AB25: =IFERROR(VLOOKUP(A25,[1]Sheet7!$A$4:$B$30,2,FALSE),0) -> 1 | AC25: =Y25+AB25 -> 1
A26: =CONCATENATE(B26,C26) -> 1B.1R | B26: 1B.1 | C26: R | D26: MKUZE | E26: INGWAVUMA | F26: =VLOOKUP(A26,'FORM I1 SUB STD NORMAL'!$A$16:$O$55,15,FALSE) -> 31 | K26: =F26-G26-H26-I26-J26-Y26 -> 31 | L26: 90 | M26: =F26*L26 -> 2790 | N26: =K26*L26 -> 2790 | O26: 1636 | Q26: =O26+P26 -> 1636 | R26: =Q26/K26 -> 52.774194 | S26: 30412 | U26: =SUM(S26:T26) -> 30412 | V26: =U26/K26 -> 981.03226 | W26: =U26/N26 -> 10.900358 | X26: =IF(Q26>0,U26/Q26,0) -> 18.589242 | Z26: =SUM(Y26*L26) -> 0 | AA26: =A26 -> 1B.1R | AB26: =IFERROR(VLOOKUP(A26,[1]Sheet7!$A$4:$B$30,2,FALSE),0) -> 1 | AC26: =Y26+AB26 -> 1
A27: =CONCATENATE(B27,C27) -> 1B2F | B27: 1B2 | C27: F | D27: INGWAVUMA | E27: MKUZE | F27: =VLOOKUP(A27,'FORM I1 SUB STD NORMAL'!$A$16:$O$55,15,FALSE) -> 26 | K27: =F27-G27-H27-I27-J27-Y27 -> 26 | L27: 85.3 | M27: =F27*L27 -> 2217.8 | N27: =K27*L27 -> 2217.8 | O27: 1576 | Q27: =O27+P27 -> 1576 | R27: =Q27/K27 -> 60.615385 | S27: 24986 | U27: =SUM(S27:T27) -> 24986 | V27: =U27/K27 -> 961 | W27: =U27/N27 -> 11.26612 | X27: =IF(Q27>0,U27/Q27,0) -> 15.854061 | Z27: =SUM(Y27*L27) -> 0 | AA27: =A27 -> 1B2F | AB27: =IFERROR(VLOOKUP(A27,[1]Sheet7!$A$4:$B$30,2,FALSE),0) -> 1 | AC27: =Y27+AB27 -> 1
A28: =CONCATENATE(B28,C28) -> 1B2R | B28: 1B2 | C28: R | D28: MKUZE | E28: INGWAVUMA | F28: =VLOOKUP(A28,'FORM I1 SUB STD NORMAL'!$A$16:$O$55,15,FALSE) -> 26 | K28: =F28-G28-H28-I28-J28-Y28 -> 26 | L28: 85.3 | M28: =F28*L28 -> 2217.8 | N28: =K28*L28 -> 2217.8 | O28: 1765 | Q28: =O28+P28 -> 1765 | R28: =Q28/K28 -> 67.884615 | S28: 27880.5 | U28: =SUM(S28:T28) -> 27880.5 | V28: =U28/K28 -> 1072.3269 | W28: =U28/N28 -> 12.571242 | X28: =IF(Q28>0,U28/Q28,0) -> 15.796317 | Z28: =SUM(Y28*L28) -> 0 | AA28: =A28 -> 1B2R | AB28: =IFERROR(VLOOKUP(A28,[1]Sheet7!$A$4:$B$30,2,FALSE),0) -> 1 | AC28: =Y28+AB28 -> 1
A29: =CONCATENATE(B29,C29) -> 1C1F | B29: 1C1 | C29: F | D29: INGWAVUMA | E29: JOZINI | F29: =VLOOKUP(A29,'FORM I1 SUB STD NORMAL'!$A$16:$O$55,15,FALSE) -> 26 | K29: =F29-G29-H29-I29-J29-Y29 -> 26 | L29: 55.5 | M29: =F29*L29 -> 1443 | N29: =K29*L29 -> 1443 | O29: 1445 | Q29: =O29+P29 -> 1445 | R29: =Q29/K29 -> 55.576923 | S29: 33890 | U29: =SUM(S29:T29) -> 33890 | V29: =U29/K29 -> 1303.4615 | W29: =U29/N29 -> 23.485793 | X29: =IF(Q29>0,U29/Q29,0) -> 23.453287 | Z29: =SUM(Y29*L29) -> 0 | AA29: =A29 -> 1C1F | AB29: =IFERROR(VLOOKUP(A29,[1]Sheet7!$A$4:$B$30,2,FALSE),0) -> 0 | AC29: =Y29+AB29 -> 0
A30: =CONCATENATE(B30,C30) -> 1C1R | B30: 1C1 | C30: R | D30: JOZINI | E30: INGWAVUMA | F30: =VLOOKUP(A30,'FORM I1 SUB STD NORMAL'!$A$16:$O$55,15,FALSE) -> 26 | K30: =F30-G30-H30-I30-J30-Y30 -> 26 | L30: 55.5 | M30: =F30*L30 -> 1443 | N30: =K30*L30 -> 1443 | O30: 1558 | Q30: =O30+P30 -> 1558 | R30: =Q30/K30 -> 59.923077 | S30: 34194 | U30: =SUM(S30:T30) -> 34194 | V30: =U30/K30 -> 1315.1538 | W30: =U30/N30 -> 23.696466 | X30: =IF(Q30>0,U30/Q30,0) -> 21.947368 | Z30: =SUM(Y30*L30) -> 0 | AA30: =A30 -> 1C1R | AB30: =IFERROR(VLOOKUP(A30,[1]Sheet7!$A$4:$B$30,2,FALSE),0) -> 0 | AC30: =Y30+AB30 -> 0
... A34: =CONCATENATE(B34,C34) -> 1DR | B34: 1D | C34: R | D34: KWA-JOHN | E34: INGWAVUMA | F34: =VLOOKUP(A34,'FORM I1 SUB STD NORMAL'!$A$16:$O$55,15,FALSE) -> 21 | K34: =F34-G34-H34-I34-J34-Y34 -> 21 | L34: 30.5 | M34: =F34*L34 -> 640.5 | N34: =K34*L34 -> 640.5 | O34: 948 | Q34: =O34+P34 -> 948 | R34: =Q34/K34 -> 45.142857 | S34: 12177 | U34: =SUM(S34:T34) -> 12177 | V34: =U34/K34 -> 579.85714 | W34: =U34/N34 -> 19.01171 | X34: =IF(Q34>0,U34/Q34,0) -> 12.844937 | Z34: =SUM(Y34*L34) -> 0 | AA34: =A34 -> 1DR | AB34: =IFERROR(VLOOKUP(A34,[1]Sheet7!$A$4:$B$30,2,FALSE),0) -> 0 | AC34: =Y34+AB34 -> 0
A35: =CONCATENATE(B35,C35) -> 2F | B35: 2 | C35: F | D35: ENGONYAMENI | E35: INGWAVUMA | F35: =VLOOKUP(A35,'FORM I1 SUB STD NORMAL'!$A$16:$O$55,15,FALSE) -> 26 | K35: =F35-G35-H35-I35-J35-Y35 -> 26 | L35: 50.2 | M35: =F35*L35 -> 1305.2 | N35: =K35*L35 -> 1305.2 | O35: 4363 | Q35: =O35+P35 -> 4363 | R35: =Q35/K35 -> 167.80769 | S35: 49450 | U35: =SUM(S35:T35) -> 49450 | V35: =U35/K35 -> 1901.9231 | W35: =U35/N35 -> 37.886914 | X35: =IF(Q35>0,U35/Q35,0) -> 11.333945 | Z35: =SUM(Y35*L35) -> 0 | AA35: =A35 -> 2F | AB35: =IFERROR(VLOOKUP(A35,[1]Sheet7!$A$4:$B$30,2,FALSE),0) -> 0 | AC35: =Y35+AB35 -> 0
A36: =CONCATENATE(B36,C36) -> 2R | B36: 2 | C36: R | D36: INGWAVUMA | E36: ENGONYAMENI | F36: =VLOOKUP(A36,'FORM I1 SUB STD NORMAL'!$A$16:$O$55,15,FALSE) -> 26 | K36: =F36-G36-H36-I36-J36-Y36 -> 26 | L36: 50.2 | M36: =F36*L36 -> 1305.2 | N36: =K36*L36 -> 1305.2 | O36: 4237 | Q36: =O36+P36 -> 4237 | R36: =Q36/K36 -> 162.96154 | S36: 43154 | U36: =SUM(S36:T36) -> 43154 | V36: =U36/K36 -> 1659.7692 | W36: =U36/N36 -> 33.063132 | X36: =IF(Q36>0,U36/Q36,0) -> 10.185037 | Z36: =SUM(Y36*L36) -> 0 | AA36: =A36 -> 2R | AB36: =IFERROR(VLOOKUP(A36,[1]Sheet7!$A$4:$B$30,2,FALSE),0) -> 0 | AC36: =Y36+AB36 -> 0
A37: =CONCATENATE(B37,C37) -> 3F | B37: 3 | C37: F | D37: ESIGAYWENI | E37: INGWAVUMA | F37: =VLOOKUP(A37,'FORM I1 SUB STD NORMAL'!$A$16:$O$55,15,FALSE) -> 26 | K37: =F37-G37-H37-I37-J37-Y37 -> 26 | L37: 80.2 | M37: =F37*L37 -> 2085.2 | N37: =K37*L37 -> 2085.2 | O37: 1192 | Q37: =O37+P37 -> 1192 | R37: =Q37/K37 -> 45.846154 | S37: 27704 | U37: =SUM(S37:T37) -> 27704 | V37: =U37/K37 -> 1065.5385 | W37: =U37/N37 -> 13.286016 | X37: =IF(Q37>0,U37/Q37,0) -> 23.241611 | Z37: =SUM(Y37*L37) -> 0 | AA37: =A37 -> 3F | AB37: =IFERROR(VLOOKUP(A37,[1]Sheet7!$A$4:$B$30,2,FALSE),0) -> 0 | AC37: =Y37+AB37 -> 0
A38: =CONCATENATE(B38,C38) -> 3R | B38: 3 | C38: R | D38: INGWAVUMA | E38: ESIGAYWENI | F38: =VLOOKUP(A38,'FORM I1 SUB STD NORMAL'!$A$16:$O$55,15,FALSE) -> 26 | K38: =F38-G38-H38-I38-J38-Y38 -> 26 | L38: 80.2 | M38: =F38*L38 -> 2085.2 | N38: =K38*L38 -> 2085.2 | O38: 1221 | Q38: =O38+P38 -> 1221 | R38: =Q38/K38 -> 46.961538 | S38: 27079 | U38: =SUM(S38:T38) -> 27079 | V38: =U38/K38 -> 1041.5 | W38: =U38/N38 -> 12.986284 | X38: =IF(Q38>0,U38/Q38,0) -> 22.177723 | Z38: =SUM(Y38*L38) -> 0 | AA38: =A38 -> 3R | AB38: =IFERROR(VLOOKUP(A38,[1]Sheet7!$A$4:$B$30,2,FALSE),0) -> 0 | AC38: =Y38+AB38 -> 0
A39: =CONCATENATE(B39,C39) -> 5F | B39: 5 | C39: F | D39: EKUKHANYENI | E39: MKUZE | F39: =VLOOKUP(A39,'FORM I1 SUB STD NORMAL'!$A$16:$O$55,15,FALSE) -> 26 | K39: =F39-G39-H39-I39-J39-Y39 -> 25 | L39: 117 | M39: =F39*L39 -> 3042 | N39: =K39*L39 -> 2925 | O39: 1603 | Q39: =O39+P39 -> 1603 | R39: =Q39/K39 -> 64.12 | S39: 29349 | U39: =SUM(S39:T39) -> 29349 | V39: =U39/K39 -> 1173.96 | W39: =U39/N39 -> 10.033846 | X39: =IF(Q39>0,U39/Q39,0) -> 18.308796 | Y39: 1 | Z39: =SUM(Y39*L39) -> 117 | AA39: =A39 -> 5F | AB39: =IFERROR(VLOOKUP(A39,[1]Sheet7!$A$4:$B$30,2,FALSE),0) -> 1 | AC39: =Y39+AB39 -> 2
A40: =CONCATENATE(B40,C40) -> 5R | B40: 5 | C40: R | D40: MKUZE | E40: EKUKHANYENI | F40: =VLOOKUP(A40,'FORM I1 SUB STD NORMAL'!$A$16:$O$55,15,FALSE) -> 26 | K40: =F40-G40-H40-I40-J40-Y40 -> 25 | L40: 117 | M40: =F40*L40 -> 3042 | N40: =K40*L40 -> 2925 | O40: 1636 | Q40: =O40+P40 -> 1636 | R40: =Q40/K40 -> 65.44 | S40: 31854 | U40: =SUM(S40:T40) -> 31854 | V40: =U40/K40 -> 1274.16 | W40: =U40/N40 -> 10.890256 | X40: =IF(Q40>0,U40/Q40,0) -> 19.47066 | Y40: 1 | Z40: =SUM(Y40*L40) -> 117 | AA40: =A40 -> 5R | AB40: =IFERROR(VLOOKUP(A40,[1]Sheet7!$A$4:$B$30,2,FALSE),0) -> 1 | AC40: =Y40+AB40 -> 2
A41: =CONCATENATE(B41,C41) -> 6AF | B41: 6A | C41: F | D41: MANGUZE | E41: MKUZE | F41: =VLOOKUP(A41,'FORM I1 SUB STD NORMAL'!$A$16:$O$55,15,FALSE) -> 36 | K41: =F41-G41-H41-I41-J41-Y41 -> 36 | L41: 149.9 | M41: =F41*L41 -> 5396.4 | N41: =K41*L41 -> 5396.4 | O41: 1428 | Q41: =O41+P41 -> 1428 | R41: =Q41/K41 -> 39.666667 | S41: 32903.5 | U41: =SUM(S41:T41) -> 32903.5 | V41: =U41/K41 -> 913.98611 | W41: =U41/N41 -> 6.0973056 | X41: =IF(Q41>0,U41/Q41,0) -> 23.041667 | Z41: =SUM(Y41*L41) -> 0 | AA41: =A41 -> 6AF | AB41: =IFERROR(VLOOKUP(A41,[1]Sheet7!$A$4:$B$30,2,FALSE),0) -> 1 | AC41: =Y41+AB41 -> 1
A42: =CONCATENATE(B42,C42) -> 6AR | B42: 6A | C42: R | D42: MKUZE | E42: MANGUZE | F42: =VLOOKUP(A42,'FORM I1 SUB STD NORMAL'!$A$16:$O$55,15,FALSE) -> 26 | K42: =F42-G42-H42-I42-J42-Y42 -> 26 | L42: 149.9 | M42: =F42*L42 -> 3897.4 | N42: =K42*L42 -> 3897.4 | O42: 1382 | Q42: =O42+P42 -> 1382 | R42: =Q42/K42 -> 53.153846 | S42: 31723.5 | U42: =SUM(S42:T42) -> 31723.5 | V42: =U42/K42 -> 1220.1346 | W42: =U42/N42 -> 8.1396572 | X42: =IF(Q42>0,U42/Q42,0) -> 22.954776 | Z42: =SUM(Y42*L42) -> 0 | AA42: =A42 -> 6AR | AB42: =IFERROR(VLOOKUP(A42,[1]Sheet7!$A$4:$B$30,2,FALSE),0) -> 1 | AC42: =Y42+AB42 -> 1
A43: =CONCATENATE(B43,C43) -> 6BF | B43: 6B | C43: F | D43: MBUYISA | E43: MKUZE | F43: =VLOOKUP(A43,'FORM I1 SUB STD NORMAL'!$A$16:$O$55,15,FALSE) -> 21 | K43: =F43-G43-H43-I43-J43-Y43 -> 21 | L43: 97.5 | M43: =F43*L43 -> 2047.5 | N43: =K43*L43 -> 2047.5 | O43: 978 | Q43: =O43+P43 -> 978 | R43: =Q43/K43 -> 46.571429 | S43: 27186 | U43: =SUM(S43:T43) -> 27186 | V43: =U43/K43 -> 1294.5714 | W43: =U43/N43 -> 13.277656 | X43: =IF(Q43>0,U43/Q43,0) -> 27.797546 | Z43: =SUM(Y43*L43) -> 0 | AA43: =A43 -> 6BF | AB43: =IFERROR(VLOOKUP(A43,[1]Sheet7!$A$4:$B$30,2,FALSE),0) -> 1 | AC43: =Y43+AB43 -> 1
A44: =CONCATENATE(B44,C44) -> 6BR | B44: 6B | C44: R | D44: MKUZE | E44: MBUYISA | F44: =VLOOKUP(A44,'FORM I1 SUB STD NORMAL'!$A$16:$O$55,15,FALSE) -> 26 | K44: =F44-G44-H44-I44-J44-Y44 -> 26 | L44: 97.5 | M44: =F44*L44 -> 2535 | N44: =K44*L44 -> 2535 | O44: 1165 | Q44: =O44+P44 -> 1165 | R44: =Q44/K44 -> 44.807692 | S44: 25938 | U44: =SUM(S44:T44) -> 25938 | V44: =U44/K44 -> 997.61538 | W44: =U44/N44 -> 10.231953 | X44: =IF(Q44>0,U44/Q44,0) -> 22.264378 | Z44: =SUM(Y44*L44) -> 0 | AA44: =A44 -> 6BR | AB44: =IFERROR(VLOOKUP(A44,[1]Sheet7!$A$4:$B$30,2,FALSE),0) -> 1 | AC44: =Y44+AB44 -> 1
A45: =CONCATENATE(B45,C45) -> 6CF | B45: 6C | C45: F | D45: JOZINI | E45: MKUZE | F45: =VLOOKUP(A45,'FORM I1 SUB STD NORMAL'!$A$16:$O$55,15,FALSE) -> 26 | K45: =F45-G45-H45-I45-J45-Y45 -> 26 | L45: 41 | M45: =F45*L45 -> 1066 | N45: =K45*L45 -> 1066 | O45: 1198 | Q45: =O45+P45 -> 1198 | R45: =Q45/K45 -> 46.076923 | S45: 16324 | U45: =SUM(S45:T45) -> 16324 | V45: =U45/K45 -> 627.84615 | W45: =U45/N45 -> 15.313321 | X45: =IF(Q45>0,U45/Q45,0) -> 13.626043 | Z45: =SUM(Y45*L45) -> 0 | AA45: =A45 -> 6CF | AB45: =IFERROR(VLOOKUP(A45,[1]Sheet7!$A$4:$B$30,2,FALSE),0) -> 1 | AC45: =Y45+AB45 -> 1
A46: =CONCATENATE(B46,C46) -> 6CR | B46: 6C | C46: R | D46: MKUZE | E46: JOZINI | F46: =VLOOKUP(A46,'FORM I1 SUB STD NORMAL'!$A$16:$O$55,15,FALSE) -> 26 | K46: =F46-G46-H46-I46-J46-Y46 -> 26 | L46: 41 | M46: =F46*L46 -> 1066 | N46: =K46*L46 -> 1066 | O46: 1175 | Q46: =O46+P46 -> 1175 | R46: =Q46/K46 -> 45.192308 | S46: 13250 | U46: =SUM(S46:T46) -> 13250 | V46: =U46/K46 -> 509.61538 | W46: =U46/N46 -> 12.429644 | X46: =IF(Q46>0,U46/Q46,0) -> 11.276596 | Z46: =SUM(Y46*L46) -> 0 | AA46: =A46 -> 6CR | AB46: =IFERROR(VLOOKUP(A46,[1]Sheet7!$A$4:$B$30,2,FALSE),0) -> 1 | AC46: =Y46+AB46 -> 1
A47: =CONCATENATE(B47,C47) -> 7AF | B47: 7A | C47: F | D47: MANGUZE | E47: MKUZE | F47: =VLOOKUP(A47,'FORM I1 SUB STD NORMAL'!$A$16:$O$55,15,FALSE) -> 21 | K47: =F47-G47-H47-I47-J47-Y47 -> 21 | L47: 136.5 | M47: =F47*L47 -> 2866.5 | N47: =K47*L47 -> 2866.5 | O47: 960 | Q47: =O47+P47 -> 960 | R47: =Q47/K47 -> 45.714286 | S47: 17323.5 | U47: =SUM(S47:T47) -> 17323.5 | V47: =U47/K47 -> 824.92857 | W47: =U47/N47 -> 6.0434328 | X47: =IF(Q47>0,U47/Q47,0) -> 18.045313 | Z47: =SUM(Y47*L47) -> 0 | AA47: =A47 -> 7AF | AB47: =IFERROR(VLOOKUP(A47,[1]Sheet7!$A$4:$B$30,2,FALSE),0) -> 1 | AC47: =Y47+AB47 -> 1
A48: =CONCATENATE(B48,C48) -> 7AR | B48: 7A | C48: R | D48: MKUZE | E48: MANGUZE | F48: =VLOOKUP(A48,'FORM I1 SUB STD NORMAL'!$A$16:$O$55,15,FALSE) -> 26 | K48: =F48-G48-H48-I48-J48-Y48 -> 26 | L48: 136.5 | M48: =F48*L48 -> 3549 | N48: =K48*L48 -> 3549 | O48: 1179 | Q48: =O48+P48 -> 1179 | R48: =Q48/K48 -> 45.346154 | S48: 17371.5 | U48: =SUM(S48:T48) -> 17371.5 | V48: =U48/K48 -> 668.13462 | W48: =U48/N48 -> 4.8947591 | X48: =IF(Q48>0,U48/Q48,0) -> 14.734097 | Z48: =SUM(Y48*L48) -> 0 | AA48: =A48 -> 7AR | AB48: =IFERROR(VLOOKUP(A48,[1]Sheet7!$A$4:$B$30,2,FALSE),0) -> 1 | AC48: =Y48+AB48 -> 1
A49: =CONCATENATE(B49,C49) -> 7CF | B49: 7C | C49: F | D49: NGUTSHANA | E49: MKUZE | F49: =VLOOKUP(A49,'FORM I1 SUB STD NORMAL'!$A$16:$O$55,15,FALSE) -> 31 | K49: =F49-G49-H49-I49-J49-Y49 -> 31 | L49: 117.5 | M49: =F49*L49 -> 3642.5 | N49: =K49*L49 -> 3642.5 | O49: 1380 | Q49: =O49+P49 -> 1380 | R49: =Q49/K49 -> 44.516129 | S49: 23729.5 | U49: =SUM(S49:T49) -> 23729.5 | V49: =U49/K49 -> 765.46774 | W49: =U49/N49 -> 6.5146191 | X49: =IF(Q49>0,U49/Q49,0) -> 17.19529 | Z49: =SUM(Y49*L49) -> 0 | AA49: =A49 -> 7CF | AB49: =IFERROR(VLOOKUP(A49,[1]Sheet7!$A$4:$B$30,2,FALSE),0) -> 1 | AC49: =Y49+AB49 -> 1
A50: =CONCATENATE(B50,C50) -> 7CR | B50: 7C | C50: R | D50: MKUZE | E50: NGUTSHANA | F50: =VLOOKUP(A50,'FORM I1 SUB STD NORMAL'!$A$16:$O$55,15,FALSE) -> 31 | K50: =F50-G50-H50-I50-J50-Y50 -> 31 | L50: 117.5 | M50: =F50*L50 -> 3642.5 | N50: =K50*L50 -> 3642.5 | O50: 1443 | Q50: =O50+P50 -> 1443 | R50: =Q50/K50 -> 46.548387 | S50: 23145 | U50: =SUM(S50:T50) -> 23145 | V50: =U50/K50 -> 746.6129 | W50: =U50/N50 -> 6.3541524 | X50: =IF(Q50>0,U50/Q50,0) -> 16.039501 | Z50: =SUM(Y50*L50) -> 0 | AA50: =A50 -> 7CR | AB50: =IFERROR(VLOOKUP(A50,[1]Sheet7!$A$4:$B$30,2,FALSE),0) -> 1 | AC50: =Y50+AB50 -> 1
A51: =CONCATENATE(B51,C51) -> 8F | B51: 8 | C51: F | D51: MANABA | E51: MKUZE | F51: =VLOOKUP(A51,'FORM I1 SUB STD NORMAL'!$A$16:$O$55,15,FALSE) -> 21 | K51: =F51-G51-H51-I51-J51-Y51 -> 21 | L51: 78.8 | M51: =F51*L51 -> 1654.8 | N51: =K51*L51 -> 1654.8 | O51: 966 | Q51: =O51+P51 -> 966 | R51: =Q51/K51 -> 46 | S51: 12473 | U51: =SUM(S51:T51) -> 12473 | V51: =U51/K51 -> 593.95238 | W51: =U51/N51 -> 7.5374668 | X51: =IF(Q51>0,U51/Q51,0) -> 12.912008 | Z51: =SUM(Y51*L51) -> 0 | AA51: =A51 -> 8F | AB51: =IFERROR(VLOOKUP(A51,[1]Sheet7!$A$4:$B$30,2,FALSE),0) -> 1 | AC51: =Y51+AB51 -> 1
A52: =CONCATENATE(B52,C52) -> 8R | B52: 8 | C52: R | D52: MKUZE | E52: MANABA | F52: =VLOOKUP(A52,'FORM I1 SUB STD NORMAL'!$A$16:$O$55,15,FALSE) -> 21 | K52: =F52-G52-H52-I52-J52-Y52 -> 21 | L52: 78.8 | M52: =F52*L52 -> 1654.8 | N52: =K52*L52 -> 1654.8 | O52: 951 | Q52: =O52+P52 -> 951 | R52: =Q52/K52 -> 45.285714 | S52: 12588 | U52: =SUM(S52:T52) -> 12588 | V52: =U52/K52 -> 599.42857 | W52: =U52/N52 -> 7.6069616 | X52: =IF(Q52>0,U52/Q52,0) -> 13.236593 | Z52: =SUM(Y52*L52) -> 0 | AA52: =A52 -> 8R | AB52: =IFERROR(VLOOKUP(A52,[1]Sheet7!$A$4:$B$30,2,FALSE),0) -> 1 | AC52: =Y52+AB52 -> 1
A53: =CONCATENATE(B53,C53) -> 9AF | B53: 9A | C53: F | D53: KWA-MAZIBUKO TERMINUS | E53: MKUZE TERMINUS | F53: =VLOOKUP(A53,'FORM I1 SUB STD NORMAL'!$A$16:$O$55,15,FALSE) -> 26 | K53: =F53-G53-H53-I53-J53-Y53 -> 26 | L53: 70.3 | M53: =F53*L53 -> 1827.8 | N53: =K53*L53 -> 1827.8 | O53: 1169 | Q53: =O53+P53 -> 1169 | R53: =Q53/K53 -> 44.961538 | S53: 18446 | U53: =SUM(S53:T53) -> 18446 | V53: =U53/K53 -> 709.46154 | W53: =U53/N53 -> 10.091914 | X53: =IF(Q53>0,U53/Q53,0) -> 15.779299 | Z53: =SUM(Y53*L53) -> 0 | AA53: =A53 -> 9AF | AB53: =IFERROR(VLOOKUP(A53,[1]Sheet7!$A$4:$B$30,2,FALSE),0) -> 1 | AC53: =Y53+AB53 -> 1
A54: =CONCATENATE(B54,C54) -> 9AR | B54: 9A | C54: R | D54: MKUZE TERMINUS | E54: KWA-MAZIBUKO TERMINUS | F54: =VLOOKUP(A54,'FORM I1 SUB STD NORMAL'!$A$16:$O$55,15,FALSE) -> 26 | K54: =F54-G54-H54-I54-J54-Y54 -> 26 | L54: 70.3 | M54: =F54*L54 -> 1827.8 | N54: =K54*L54 -> 1827.8 | O54: 1205 | Q54: =O54+P54 -> 1205 | R54: =Q54/K54 -> 46.346154 | S54: 19450 | U54: =SUM(S54:T54) -> 19450 | V54: =U54/K54 -> 748.07692 | W54: =U54/N54 -> 10.641208 | X54: =IF(Q54>0,U54/Q54,0) -> 16.141079 | Z54: =SUM(Y54*L54) -> 0 | AA54: =A54 -> 9AR | AB54: =IFERROR(VLOOKUP(A54,[1]Sheet7!$A$4:$B$30,2,FALSE),0) -> 1 | AC54: =Y54+AB54 -> 1
A55: =CONCATENATE(B55,C55) -> 9BF | B55: 9B | C55: F | D55: HLABISA TERMINUS | E55: MKUZE TERMINUS | F55: =VLOOKUP(A55,'FORM I1 SUB STD NORMAL'!$A$16:$O$55,15,FALSE) -> 26 | K55: =F55-G55-H55-I55-J55-Y55 -> 26 | L55: 78 | M55: =F55*L55 -> 2028 | N55: =K55*L55 -> 2028 | O55: 1190 | Q55: =O55+P55 -> 1190 | R55: =Q55/K55 -> 45.769231 | S55: 16236 | U55: =SUM(S55:T55) -> 16236 | V55: =U55/K55 -> 624.46154 | W55: =U55/N55 -> 8.0059172 | X55: =IF(Q55>0,U55/Q55,0) -> 13.643697 | Z55: =SUM(Y55*L55) -> 0 | AA55: =A55 -> 9BF | AB55: =IFERROR(VLOOKUP(A55,[1]Sheet7!$A$4:$B$30,2,FALSE),0) -> 1 | AC55: =Y55+AB55 -> 1
A56: =CONCATENATE(B56,C56) -> 9BR | B56: 9B | C56: R | D56: MKUZE TERMINUS | E56: HLABISATERMINUS | F56: =VLOOKUP(A56,'FORM I1 SUB STD NORMAL'!$A$16:$O$55,15,FALSE) -> 26 | K56: =F56-G56-H56-I56-J56-Y56 -> 26 | L56: 78 | M56: =F56*L56 -> 2028 | N56: =K56*L56 -> 2028 | O56: 1215 | Q56: =O56+P56 -> 1215 | R56: =Q56/K56 -> 46.730769 | S56: 16682.5 | U56: =SUM(S56:T56) -> 16682.5 | V56: =U56/K56 -> 641.63462 | W56: =U56/N56 -> 8.2260848 | X56: =IF(Q56>0,U56/Q56,0) -> 13.730453 | Z56: =SUM(Y56*L56) -> 0 | AA56: =A56 -> 9BR | AB56: =IFERROR(VLOOKUP(A56,[1]Sheet7!$A$4:$B$30,2,FALSE),0) -> 1 | AC56: =Y56+AB56 -> 1
B58: TOTALS TO FORM E | F58: =SUM(F17:F56) -> 998 | G58: =SUM(G17:G56) -> 0 | H58: =SUM(H17:H56) -> 0 | I58: =SUM(I17:I56) -> 0 | J58: =SUM(J17:J56) -> 0 | K58: =SUM(K17:K56) -> 996 | M58: =SUM(M17:M56) -> 82763.4 | N58: =SUM(N17:N56) -> 82529.4 | O58: =SUM(O17:O56) -> 58044 | P58: =SUM(P17:P56) -> 0 | Q58: =SUM(Q17:Q56) -> 58044 | R58: =Q58/K58 -> 58.277108 | S58: =SUM(S17:S56) -> 1023296 | T58: =SUM(T17:T56) -> 0 | U58: =SUM(U17:U56) -> 1023296 | V58: =U58/K58 -> 1027.4056 | W58: =U58/N58 -> 12.399169 | X58: =IF(Q58>0,U58/Q58,0) -> 17.62966 | Y58: =SUM(Y17:Y56) -> 2 | Z58: =SUM(Z17:Z56) -> 234
M61: =M58-N58 -> 234
I66: =I67-N58 -> #REF!
H67: ='FORM I1 SUB STD NORMAL'!O57+#REF! -> #REF! | I67: ='FORM I1 SUB STD NORMAL'!P57+#REF! -> #REF!

Sheet FORM F2 UNSUB - STD BUS 
B1: FORM F2 - STANDARD BUS
B3: PUBLIC TRANSPORT : | E3: ='FORM F1 SUB - STD BUS'!E3 -> PROVISION OF PUBLIC PASSENGER TRANSPORT MKUZE AND SURROUNDING
B5: ='FORM F1 SUB - STD BUS'!B5 -> CONTRACT : ZNT 1129 | M5: OPERATOR : | O5: ='FORM F1 SUB - STD BUS'!O5 -> Ripple Effect 40 (Pty) Ltd
B7: CERTIFICATE NO.: | E7: ='FORM F1 SUB - STD BUS'!E7 -> 320 | M7: FOR MONTH : | O7: ='FORM F1 SUB - STD BUS'!O7 -> 45778
B9: OPERATIONAL STATISTICS: UNSUBSIDISED SERVICES
D12: ROUTE | F12: TRIPS | L12: Route | M12: KILOMETRES | O12: PASSENGERS | S12: PASSENGER REVENUE | Y12: STANDING
L13: Length | R13: Avg | V13: Avg | W13: Avg | X13: Avg
B14: No | C14: F/R | D14: From | E14: To | F14: Scheduled | G14: DNOs | H14: Late | I14: Break | J14: Non Com | K14: Operated | M14: Scheduled | N14: Operated | O14: Cash | P14: Season | Q14: Total | R14: pass/trip | S14: Cash | T14: Season | U14: Total | V14: rev/trip | W14: rev/rev km | X14: rev/pass | Y14: Trips | Z14: Kilometes
F15: ` | H15: > 30 min. | I15: Down | J15: CRW | M15: (5x11) | N15: (10x11) | Q15: (14+15) | R15: (14/10) | U15: (18+19) | V15: (20/10) | W15: (20/13) | X15: (20/16) | Z15: (24x11)
B16: 1 | C16: =B16+1 -> 2 | D16: =C16+1 -> 3 | E16: =D16+1 -> 4 | F16: =E16+1 -> 5 | G16: =F16+1 -> 6 | H16: =G16+1 -> 7 | I16: =H16+1 -> 8 | J16: =I16+1 -> 9 | ... Z16: =Y16+1 -> 25
A17: =CONCATENATE(B17,C17) -> 4R | B17: 4 | C17: R | D17: MANGUZI | E17: INGWAVUMA | F17: =VLOOKUP(B17,'FORM I2 UNSUB STD '!$B$16:$O$20,14,FALSE) -> 42 | K17: =F17-G17-H17-I17-J17-Y17 -> 42 | L17: 98.9 | M17: =F17*L17 -> 4153.8 | N17: =K17*L17 -> 4153.8 | O17: 1896 | Q17: =O17+P17 -> 1896 | R17: =Q17/K17 -> 45.142857 | S17: 16002.5 | U17: =SUM(S17:T17) -> 16002.5 | V17: =U17/K17 -> 381.0119 | W17: =U17/N17 -> 3.8524965 | X17: =IF(Q17>0,U17/Q17,0) -> 8.4401371 | Z17: =SUM(Y17*L17) -> 0
A18: =CONCATENATE(B18,C18) -> 8F | B18: 8 | C18: F | D18: MANABA | E18: MKUZE | F18: =VLOOKUP(B18,'FORM I2 UNSUB STD '!$B$16:$O$20,14,FALSE) -> 10 | K18: =F18-G18-H18-I18-J18-Y18 -> 10 | L18: 78.8 | M18: =F18*L18 -> 788 | N18: =K18*L18 -> 788 | O18: 452 | Q18: =O18+P18 -> 452 | R18: =Q18/K18 -> 45.2 | S18: 5846 | U18: =SUM(S18:T18) -> 5846 | V18: =U18/K18 -> 584.6 | W18: =U18/N18 -> 7.4187817 | X18: =IF(Q18>0,U18/Q18,0) -> 12.933628 | Z18: =SUM(Y18*L18) -> 0
A19: =CONCATENATE(B19,C19) -> 11AR | B19: 11A | C19: R | D19: MKUZE | E19: EMPANGENI | F19: =VLOOKUP(B19,'FORM I2 UNSUB STD '!$B$16:$O$20,14,FALSE) -> 42 | K19: =F19-G19-H19-I19-J19-Y19 -> 42 | L19: 125.6 | M19: =F19*L19 -> 5275.2 | N19: =K19*L19 -> 5275.2 | O19: 1903 | Q19: =O19+P19 -> 1903 | R19: =Q19/K19 -> 45.309524 | S19: 44034.5 | U19: =SUM(S19:T19) -> 44034.5 | V19: =U19/K19 -> 1048.4405 | W19: =U19/N19 -> 8.347456 | X19: =IF(Q19>0,U19/Q19,0) -> 23.139517 | Z19: =SUM(Y19*L19) -> 0
A20: =CONCATENATE(B20,C20) -> 11BF | B20: 11B | C20: F | D20: MANABA | E20: EMPANGENI | F20: =VLOOKUP(B20,'FORM I2 UNSUB STD '!$B$16:$O$20,14,FALSE) -> 18 | K20: =F20-G20-H20-I20-J20-Y20 -> 18 | L20: 224.9 | M20: =F20*L20 -> 4048.2 | N20: =K20*L20 -> 4048.2 | Q20: =O20+P20 -> 0 | R20: =Q20/K20 -> 0 | U20: =SUM(S20:T20) -> 0 | V20: =U20/K20 -> 0 | W20: =U20/N20 -> 0 | X20: =IF(Q20>0,U20/Q20,0) -> 0 | Z20: =SUM(Y20*L20) -> 0
A21: =CONCATENATE(B21,C21) -> 19AR | B21: 19A | C21: R | D21: MKUZE | E21: MHLEKAZI | F21: =VLOOKUP(B21,'FORM I2 UNSUB STD '!$B$16:$O$20,14,FALSE) -> 52 | K21: =F21-G21-H21-I21-J21-Y21 -> 52 | L21: 40 | M21: =F21*L21 -> 2080 | N21: =K21*L21 -> 2080 | O21: 2384 | Q21: =O21+P21 -> 2384 | R21: =Q21/K21 -> 45.846154 | S21: 26407.5 | U21: =SUM(S21:T21) -> 26407.5 | V21: =U21/K21 -> 507.83654 | W21: =U21/N21 -> 12.695913 | X21: =IF(Q21>0,U21/Q21,0) -> 11.076971 | Z21: =SUM(Y21*L21) -> 0
B23: TOTALS TO FORM E | F23: =SUM(F17:F21) -> 164 | G23: =SUM(G17:G21) -> 0 | H23: =SUM(H17:H21) -> 0 | I23: =SUM(I17:I21) -> 0 | J23: =SUM(J17:J21) -> 0 | K23: =SUM(K17:K21) -> 164 | M23: =SUM(M17:M21) -> 16345.2 | N23: =SUM(N17:N21) -> 16345.2 | O23: =SUM(O17:O21) -> 6635 | P23: =SUM(P17:P21) -> 0 | Q23: =SUM(Q17:Q21) -> 6635 | R23: =Q23/K23 -> 40.457317 | S23: =SUM(S17:S21) -> 92290.5 | T23: =SUM(T17:T21) -> 0 | U23: =SUM(U17:U21) -> 92290.5 | V23: =U23/K23 -> 562.74695 | W23: =U23/N23 -> 5.6463365 | X23: =IF(Q23>0,U23/Q23,0) -> 13.909646 | Y23: =SUM(Y17:Y21) -> 0 | Z23: =SUM(Z17:Z21) -> 0
J31: =I32-N23 -> 141384
H32: ='[2]FORM I1 SUB STD NORMAL'!N186+'[2]FORM I1 SUB STD SCHOOL H'!N183+'[2]FORM I1 SUB STD PUBLIC HOLIDAY'!O186 -> 4282 | I32: ='[2]FORM I1 SUB STD NORMAL'!O186+'[2]FORM I1 SUB STD SCHOOL H'!O183+'[2]FORM I1 SUB STD PUBLIC HOLIDAY'!P186 -> 157729.2

Sheet FORM G1
A1: FORM G1 - DETAILS OF PENALTIES
A3: PUBLIC TRANSPORT : | E3: ='FORM A'!C3 -> PROVISION OF PUBLIC PASSENGER TRANSPORT MKUZE AND SURROUNDING
A5: ='FORM A'!A6 -> CONTRACT : ZNT 1129 | I5: OPERATOR : | J5: ='FORM A'!F6 -> Ripple Effect 40 (Pty) Ltd
A7: PAYMENT CERTIFICATE NO.: | E7: ='FORM A'!C8 -> 320 | I7: FOR MONTH: | J7: ='FORM A'!F8 -> 45778
A9: LIST OF MONTHLY PENALTIES:
A11: Date | B11: Route | C11: Shift | D11: Bus | E11: TIME | H11: Place | I11: ROUTE | K11: Penalty | L11: Route | M11: RATE | N11: Penalty | O11: Penalty | P11: Displayed | Q11: Ref
B12: Number | C12: Number | D12: Number | E12: Sched | F12: CH-P | G12: Actual | I12: From | J12: To | K12: Code | L12: Length | M12: (R) | N12: (%) | O12: (R) | Q12: No
A13: 1 | B13: 2 | C13: 3 | D13: 4 | E13: 5 | F13: 6 | G13: 7 | H13: 8 | I13: 9 | J13: 10 | K13: 11 | L13: 12 | M13: 13 | N13: 14 | O13: 15 | P13: 16 | Q13: 17
A14: 45779 | B14: 9a | C14: 25 | D14: 1021 | E14: 12:h00 | F14: 12:h00 | G14: 12:h10 | H14: MKUZE | I14: mkuze | J14: mazibuko | K14: 2 | L14: =VLOOKUP(B14,'FORM F1 SUB - STD BUS'!$B$17:L56,11,FALSE) -> 70.3 | M14: 8.21 | N14: 0.25 | O14: =ROUND(L14*M14*N14,2) -> 144.29 | Q14: OP
A15: 45779 | B15: 9b | C15: 26 | D15: 1007 | E15: 14:h00 | F15: 14:h00 | G15: 14:h13 | H15: MKUZE | I15: mkuze | J15: hlabisa | K15: 2 | L15: =VLOOKUP(B15,'FORM F1 SUB - STD BUS'!$B$17:L57,11,FALSE) -> 78 | M15: 8.21 | N15: 0.25 | O15: =ROUND(L15*M15*N15,2) -> 160.1 | Q15: OP
A16: 45782 | B16: 8 | C16: 24 | D16: 1026 | E16: 12:h30 | F16: 12:h30 | G16: 12:h40 | H16: MKUZE | I16: mkuze | J16: manaba | K16: 2 | L16: =VLOOKUP(B16,'FORM F1 SUB - STD BUS'!$B$17:L58,11,FALSE) -> 78.8 | M16: 8.21 | N16: 0.25 | O16: =ROUND(L16*M16*N16,2) -> 161.74 | Q16: OP
A17: 45786 | B17: 1a1 | C17: 2 | D17: 1019 | E17: 14:h00 | F17: 14:h00 | G17: 14:h13 | H17: MKUZE | I17: mkuze | J17: emachobeni | K17: 2 | L17: =VLOOKUP(B17,'FORM F1 SUB - STD BUS'!$B$17:L62,11,FALSE) -> 81.8 | M17: 8.21 | N17: 0.25 | O17: =ROUND(L17*M17*N17,2) -> 167.89 | Q17: TESS/OP
A18: 45790 | B18: 8 | C18: 24 | D18: 1025 | E18: 12:h30 | F18: 12:h30 | G18: 12:h44 | H18: MKUZE | I18: mkuze | J18: manaba | K18: 2 | L18: =VLOOKUP(B18,'FORM F1 SUB - STD BUS'!$B$17:L63,11,FALSE) -> 78.8 | M18: 8.21 | N18: 0.25 | O18: =ROUND(L18*M18*N18,2) -> 161.74 | Q18: TESS/OP
A19: 45798 | B19: 9b | C19: 26 | D19: 1028 | E19: 14:h00 | F19: 14:h00 | G19: 14:h10 | H19: MKUZE | I19: mkuze | J19: hlabisa | K19: 2 | L19: =VLOOKUP(B19,'FORM F1 SUB - STD BUS'!$B$17:L60,11,FALSE) -> 78 | M19: 8.21 | N19: 0.25 | O19: =ROUND(L19*M19*N19,2) -> 160.1 | Q19: OP
A20: 45800 | B20: 8 | C20: 24 | D20: 1034 | E20: 12:h30 | F20: 12:h30 | G20: 12:h44 | H20: MKUZE | I20: mkuze | J20: manaba | K20: 2 | L20: =VLOOKUP(B20,'FORM F1 SUB - STD BUS'!$B$17:L61,11,FALSE) -> 78.8 | M20: 8.21 | N20: 0.25 | O20: =ROUND(L20*M20*N20,2) -> 161.74 | Q20: OP
A21: 45790 | B21: 7c | C21: 22 | D21: 1026 | E21: 13:h00 | F21: 13:h00 | G21: 13:h17 | H21: MKUZE | I21: mkuze | J21: ngutshana | K21: 3 | L21: =VLOOKUP(B21,'FORM F1 SUB - STD BUS'!$B$17:L59,11,FALSE) -> 117.5 | M21: 8.21 | N21: 0.4 | O21: =ROUND(L21*M21*N21,2) -> 385.87 | Q21: OP
A22: 45792 | B22: 7C | C22: 22 | D22: 1032 | E22: 13:H00 | F22: 13:H00 | G22: 13:H19 | H22: MKUZE | I22: mkuze | J22: ngutshana | K22: 3 | L22: =VLOOKUP(B22,'FORM F1 SUB - STD BUS'!$B$17:L64,11,FALSE) -> 117.5 | M22: 8.21 | N22: 0.4 | O22: =ROUND(L22*M22*N22,2) -> 385.87 | Q22: TESS/OP
M33: Total | O33: =SUM(O14:O32) -> 1889.34
M34: Double Pen
A35: Codes | B35: Description | E35: Pen | F35: Pen % | G35: Min Penalty | H35: Double Penalty | M35: TOTAL | O35: =O33+O34 -> 1889.34
A36: 1 | B36: FAILED TO OPERATE | F36: 0.4 | G36: 100 | H36: YES
A37: 2 | B37: LATE > 5 MIN | F37: 0.25 | H37: YES
A38: 3 | B38: LATE > 15 MIN | F38: 0.4 | H38: YES
A39: 4 | B39: LATE > 30 MIN | F39: 0 | H39: YES
A40: 5 | B40: TRIP OPERATED EARLY | F40: 0.4 | H40: YES
A41: 6 | B41: BREAKDOWN OR LATE REPLACEMENT | F41: 0.4 | H41: No
A42: 7 | B42: INCORRECT OR NO DESTINATION SHOWN | E42: 100 | F42: 0 | H42: No
A43: 8 | B43: INCORRECT OR NO DUTY DISPLAYED | E43: 200 | F43: 0 | H43: No
A44: 9 | B44: FAILED TO STOP AND LOAD | E44: 60 | F44: 0 | H44: No
A45: 10.1 | B45: VEHICLE - DIRTY | E45: 30 | F45: 0 | H45: No
A46: 10.2 | B46: VEHICLE - BROKEN WINDOWS | E46: 120 | F46: 0 | H46: No
A47: 10.3 | B47: VEHICLE - SEATS TORN/BROKEN | E47: 30 | F47: 0 | H47: No
A48: 10.4 | B48: VEHICLE - DOOR BROKEN/MISSING | E48: 120 | F48: 0 | H48: No
A49: 11 | B49: DEVIATION FROM ROUTE | E49: 100 | F49: 0 | H49: No
A50: 12 | B50: NO HEAD/REAR LIGHTS | E50: 100 | F50: 0 | H50: No
A51: 13 | B51: APPROVED EE NOT USED | F51: 0.03 | H51: No
A52: 14 | B52: COF - TIME DNO | F52: 0 | H52: No
A53: 15 | B53: BUS DNO | F53: 0.4 | H53: No

Sheet FORM G2
D1: FORM G2 - SUMMARY OF PENALTIES
A3: PUBLIC TRANSPORT : | C3: ='FORM A'!C3 -> PROVISION OF PUBLIC PASSENGER TRANSPORT MKUZE AND SURROUNDING
A5: ='FORM A'!A6 -> CONTRACT : ZNT 1129 | D5: OPERATOR : | E5: ='FORM A'!F6 -> Ripple Effect 40 (Pty) Ltd
A7: PAYMENT CERTIFICATE NO.: | C7: =+'FORM G1'!E7 -> 320 | D7: FOR MONTH : | E7: ='FORM A'!F8 -> 45778
A9: MONTHLY PENALTIES - SUMMARY
A12: Penalty | B12: Number reported by
A13: code * | D13: SMF & | E13: Total | F13: Penalty | G13: Penalty | H13: Double | I13: Total
B14: Operator | C14: SMF | D14: Operator | E14: no. | F14: amount | G14: Kms | H14: Penalty
A15: 1 | B15: 2 | C15: 3 | D15: 4 | E15: 5 | F15: 6 | G15: 7 | I15: 8
A16: 1 | B16: =COUNTIFS('FORM G1'!$K$14:$K$31,'FORM G2'!$A$16:$A$33,'FORM G1'!$Q$14:$Q$31,"OP") -> 0 | C16: =COUNTIFS('FORM G1'!$K$14:$K$31,'FORM G2'!$A$16:$A$33,'FORM G1'!$Q$14:$Q$31,"TESS") -> 0 | D16: =COUNTIFS('FORM G1'!$K$14:$K$31,'FORM G2'!$A$16:$A$33,'FORM G1'!$Q$14:$Q$31,"TESS/OP") -> 0 | E16: =SUM(B16:D16) -> 0 | F16: =SUMIF('FORM G1'!$K$14:$K$31,'FORM G2'!$A$16:$A$33,'FORM G1'!$O$14:$O$31) -> 0 | G16: {=SUMIFS('FORM G1'!$L$14:$L$31,'FORM G1'!$K$14:$K$31,'FORM G2'!$A$16:$A$33)} -> 0 | I16: =F16+H16 -> 0
A17: 2 | B17: =COUNTIFS('FORM G1'!$K$14:$K$31,'FORM G2'!$A$16:$A$33,'FORM G1'!$Q$14:$Q$31,"OP") -> 5 | C17: =COUNTIFS('FORM G1'!$K$14:$K$31,'FORM G2'!$A$16:$A$33,'FORM G1'!$Q$14:$Q$31,"TESS") -> 0 | D17: =COUNTIFS('FORM G1'!$K$14:$K$31,'FORM G2'!$A$16:$A$33,'FORM G1'!$Q$14:$Q$31,"TESS/OP") -> 2 | E17: =SUM(B17:D17) -> 7 | F17: =SUMIF('FORM G1'!$K$14:$K$31,'FORM G2'!$A$16:$A$33,'FORM G1'!$O$14:$O$31) -> 1117.6 | G17: 544.5 | I17: =F17+H17 -> 1117.6
A18: 3 | B18: =COUNTIFS('FORM G1'!$K$14:$K$31,'FORM G2'!$A$16:$A$33,'FORM G1'!$Q$14:$Q$31,"OP") -> 1 | C18: =COUNTIFS('FORM G1'!$K$14:$K$31,'FORM G2'!$A$16:$A$33,'FORM G1'!$Q$14:$Q$31,"TESS") -> 0 | D18: =COUNTIFS('FORM G1'!$K$14:$K$31,'FORM G2'!$A$16:$A$33,'FORM G1'!$Q$14:$Q$31,"TESS/OP") -> 1 | E18: =SUM(B18:D18) -> 2 | F18: =SUMIF('FORM G1'!$K$14:$K$31,'FORM G2'!$A$16:$A$33,'FORM G1'!$O$14:$O$31) -> 771.74 | G18: 235 | I18: =F18+H18 -> 771.74 | K18: =G16+G19+G32+G33 -> 0
A19: 4 | B19: =COUNTIFS('FORM G1'!$K$14:$K$31,'FORM G2'!$A$16:$A$33,'FORM G1'!$Q$14:$Q$31,"OP") -> 0 | C19: =COUNTIFS('FORM G1'!$K$14:$K$31,'FORM G2'!$A$16:$A$33,'FORM G1'!$Q$14:$Q$31,"TESS") -> 0 | D19: =COUNTIFS('FORM G1'!$K$14:$K$31,'FORM G2'!$A$16:$A$33,'FORM G1'!$Q$14:$Q$31,"TESS/OP") -> 0 | E19: =SUM(B19:D19) -> 0 | F19: =SUMIF('FORM G1'!$K$14:$K$31,'FORM G2'!$A$16:$A$33,'FORM G1'!$O$14:$O$31) -> 0 | G19: 0 | I19: =F19+H19 -> 0
A20: 5 | B20: =COUNTIFS('FORM G1'!$K$14:$K$31,'FORM G2'!$A$16:$A$33,'FORM G1'!$Q$14:$Q$31,"OP") -> 0 | C20: =COUNTIFS('FORM G1'!$K$14:$K$31,'FORM G2'!$A$16:$A$33,'FORM G1'!$Q$14:$Q$31,"TESS") -> 0 | D20: =COUNTIFS('FORM G1'!$K$14:$K$31,'FORM G2'!$A$16:$A$33,'FORM G1'!$Q$14:$Q$31,"TESS/OP") -> 0 | E20: =SUM(B20:D20) -> 0 | F20: =SUMIF('FORM G1'!$K$14:$K$31,'FORM G2'!$A$16:$A$33,'FORM G1'!$O$14:$O$31) -> 0 | G20: 0 | H20: =F20 -> 0 | I20: =F20+H20 -> 0
A21: 6 | B21: =COUNTIFS('FORM G1'!$K$14:$K$31,'FORM G2'!$A$16:$A$33,'FORM G1'!$Q$14:$Q$31,"OP") -> 0 | C21: =COUNTIFS('FORM G1'!$K$14:$K$31,'FORM G2'!$A$16:$A$33,'FORM G1'!$Q$14:$Q$31,"TESS") -> 0 | D21: =COUNTIFS('FORM G1'!$K$14:$K$31,'FORM G2'!$A$16:$A$33,'FORM G1'!$Q$14:$Q$31,"TESS/OP") -> 0 | E21: =SUM(B21:D21) -> 0 | F21: =SUMIF('FORM G1'!$K$14:$K$31,'FORM G2'!$A$16:$A$33,'FORM G1'!$O$14:$O$31) -> 0 | G21: 0 | I21: =F21+H21 -> 0
A22: 7 | B22: =COUNTIFS('FORM G1'!$K$14:$K$31,'FORM G2'!$A$16:$A$33,'FORM G1'!$Q$14:$Q$31,"OP") -> 0 | C22: =COUNTIFS('FORM G1'!$K$14:$K$31,'FORM G2'!$A$16:$A$33,'FORM G1'!$Q$14:$Q$31,"TESS") -> 0 | D22: =COUNTIFS('FORM G1'!$K$14:$K$31,'FORM G2'!$A$16:$A$33,'FORM G1'!$Q$14:$Q$31,"TESS/OP") -> 0 | E22: =SUM(B22:D22) -> 0 | F22: =SUMIF('FORM G1'!$K$14:$K$31,'FORM G2'!$A$16:$A$33,'FORM G1'!$O$14:$O$31) -> 0 | G22: 0 | I22: =F22+H22 -> 0
A23: 8 | B23: =COUNTIFS('FORM G1'!$K$14:$K$31,'FORM G2'!$A$16:$A$33,'FORM G1'!$Q$14:$Q$31,"OP") -> 0 | C23: =COUNTIFS('FORM G1'!$K$14:$K$31,'FORM G2'!$A$16:$A$33,'FORM G1'!$Q$14:$Q$31,"TESS") -> 0 | D23: =COUNTIFS('FORM G1'!$K$14:$K$31,'FORM G2'!$A$16:$A$33,'FORM G1'!$Q$14:$Q$31,"TESS/OP") -> 0 | E23: =SUM(B23:D23) -> 0 | F23: =SUMIF('FORM G1'!$K$14:$K$31,'FORM G2'!$A$16:$A$33,'FORM G1'!$O$14:$O$31) -> 0 | G23: 0 | I23: =F23+H23 -> 0
A24: 9 | B24: =COUNTIFS('FORM G1'!$K$14:$K$31,'FORM G2'!$A$16:$A$33,'FORM G1'!$Q$14:$Q$31,"OP") -> 0 | C24: =COUNTIFS('FORM G1'!$K$14:$K$31,'FORM G2'!$A$16:$A$33,'FORM G1'!$Q$14:$Q$31,"TESS") -> 0 | D24: =COUNTIFS('FORM G1'!$K$14:$K$31,'FORM G2'!$A$16:$A$33,'FORM G1'!$Q$14:$Q$31,"TESS/OP") -> 0 | E24: =SUM(B24:D24) -> 0 | F24: =SUMIF('FORM G1'!$K$14:$K$31,'FORM G2'!$A$16:$A$33,'FORM G1'!$O$14:$O$31) -> 0 | G24: 0 | I24: =F24+H24 -> 0
A25: 10.1 | B25: =COUNTIFS('FORM G1'!$K$14:$K$31,'FORM G2'!$A$16:$A$33,'FORM G1'!$Q$14:$Q$31,"OP") -> 0 | C25: =COUNTIFS('FORM G1'!$K$14:$K$31,'FORM G2'!$A$16:$A$33,'FORM G1'!$Q$14:$Q$31,"TESS") -> 0 | D25: =COUNTIFS('FORM G1'!$K$14:$K$31,'FORM G2'!$A$16:$A$33,'FORM G1'!$Q$14:$Q$31,"TESS/OP") -> 0 | E25: =SUM(B25:D25) -> 0 | F25: =SUMIF('FORM G1'!$K$14:$K$31,'FORM G2'!$A$16:$A$33,'FORM G1'!$O$14:$O$31) -> 0 | G25: 0 | I25: =F25+H25 -> 0
A26: 10.2 | B26: =COUNTIFS('FORM G1'!$K$14:$K$31,'FORM G2'!$A$16:$A$33,'FORM G1'!$Q$14:$Q$31,"OP") -> 0 | C26: =COUNTIFS('FORM G1'!$K$14:$K$31,'FORM G2'!$A$16:$A$33,'FORM G1'!$Q$14:$Q$31,"TESS") -> 0 | D26: =COUNTIFS('FORM G1'!$K$14:$K$31,'FORM G2'!$A$16:$A$33,'FORM G1'!$Q$14:$Q$31,"TESS/OP") -> 0 | E26: =SUM(B26:D26) -> 0 | F26: =SUMIF('FORM G1'!$K$14:$K$31,'FORM G2'!$A$16:$A$33,'FORM G1'!$O$14:$O$31) -> 0 | G26: 0 | I26: =F26+H26 -> 0
A27: 10.3 | B27: =COUNTIFS('FORM G1'!$K$14:$K$31,'FORM G2'!$A$16:$A$33,'FORM G1'!$Q$14:$Q$31,"OP") -> 0 | C27: =COUNTIFS('FORM G1'!$K$14:$K$31,'FORM G2'!$A$16:$A$33,'FORM G1'!$Q$14:$Q$31,"TESS") -> 0 | D27: =COUNTIFS('FORM G1'!$K$14:$K$31,'FORM G2'!$A$16:$A$33,'FORM G1'!$Q$14:$Q$31,"TESS/OP") -> 0 | E27: =SUM(B27:D27) -> 0 | F27: =SUMIF('FORM G1'!$K$14:$K$31,'FORM G2'!$A$16:$A$33,'FORM G1'!$O$14:$O$31) -> 0 | G27: 0 | I27: =F27+H27 -> 0
A28: 10.4 | B28: =COUNTIFS('FORM G1'!$K$14:$K$31,'FORM G2'!$A$16:$A$33,'FORM G1'!$Q$14:$Q$31,"OP") -> 0 | C28: =COUNTIFS('FORM G1'!$K$14:$K$31,'FORM G2'!$A$16:$A$33,'FORM G1'!$Q$14:$Q$31,"TESS") -> 0 | D28: =COUNTIFS('FORM G1'!$K$14:$K$31,'FORM G2'!$A$16:$A$33,'FORM G1'!$Q$14:$Q$31,"TESS/OP") -> 0 | E28: =SUM(B28:D28) -> 0 | F28: =SUMIF('FORM G1'!$K$14:$K$31,'FORM G2'!$A$16:$A$33,'FORM G1'!$O$14:$O$31) -> 0 | G28: 0 | I28: =F28+H28 -> 0
A29: 11 | B29: =COUNTIFS('FORM G1'!$K$14:$K$31,'FORM G2'!$A$16:$A$33,'FORM G1'!$Q$14:$Q$31,"OP") -> 0 | C29: =COUNTIFS('FORM G1'!$K$14:$K$31,'FORM G2'!$A$16:$A$33,'FORM G1'!$Q$14:$Q$31,"TESS") -> 0 | D29: =COUNTIFS('FORM G1'!$K$14:$K$31,'FORM G2'!$A$16:$A$33,'FORM G1'!$Q$14:$Q$31,"TESS/OP") -> 0 | E29: =SUM(B29:D29) -> 0 | F29: =SUMIF('FORM G1'!$K$14:$K$31,'FORM G2'!$A$16:$A$33,'FORM G1'!$O$14:$O$31) -> 0 | G29: 0 | I29: =F29+H29 -> 0
A30: 12 | B30: =COUNTIFS('FORM G1'!$K$14:$K$31,'FORM G2'!$A$16:$A$33,'FORM G1'!$Q$14:$Q$31,"OP") -> 0 | C30: =COUNTIFS('FORM G1'!$K$14:$K$31,'FORM G2'!$A$16:$A$33,'FORM G1'!$Q$14:$Q$31,"TESS") -> 0 | D30: =COUNTIFS('FORM G1'!$K$14:$K$31,'FORM G2'!$A$16:$A$33,'FORM G1'!$Q$14:$Q$31,"TESS/OP") -> 0 | E30: =SUM(B30:D30) -> 0 | F30: =SUMIF('FORM G1'!$K$14:$K$31,'FORM G2'!$A$16:$A$33,'FORM G1'!$O$14:$O$31) -> 0 | G30: 0 | I30: =F30+H30 -> 0
A31: 13 | B31: =COUNTIFS('FORM G1'!$K$14:$K$31,'FORM G2'!$A$16:$A$33,'FORM G1'!$Q$14:$Q$31,"OP") -> 0 | C31: =COUNTIFS('FORM G1'!$K$14:$K$31,'FORM G2'!$A$16:$A$33,'FORM G1'!$Q$14:$Q$31,"TESS") -> 0 | D31: =COUNTIFS('FORM G1'!$K$14:$K$31,'FORM G2'!$A$16:$A$33,'FORM G1'!$Q$14:$Q$31,"TESS/OP") -> 0 | E31: =SUM(B31:D31) -> 0 | F31: =SUMIF('FORM G1'!$K$14:$K$31,'FORM G2'!$A$16:$A$33,'FORM G1'!$O$14:$O$31) -> 0 | G31: 0 | I31: =F31+H31 -> 0
A32: 14 | B32: =COUNTIFS('FORM G1'!$K$14:$K$31,'FORM G2'!$A$16:$A$33,'FORM G1'!$Q$14:$Q$31,"OP") -> 0 | C32: =COUNTIFS('FORM G1'!$K$14:$K$31,'FORM G2'!$A$16:$A$33,'FORM G1'!$Q$14:$Q$31,"TESS") -> 0 | D32: =COUNTIFS('FORM G1'!$K$14:$K$31,'FORM G2'!$A$16:$A$33,'FORM G1'!$Q$14:$Q$31,"TESS/OP") -> 0 | E32: =SUM(B32:D32) -> 0 | F32: =SUMIF('FORM G1'!$K$14:$K$31,'FORM G2'!$A$16:$A$33,'FORM G1'!$O$14:$O$31) -> 0 | G32: 0 | I32: =F32+H32 -> 0
A33: 15 | B33: =COUNTIFS('FORM G1'!$K$14:$K$31,'FORM G2'!$A$16:$A$33,'FORM G1'!$Q$14:$Q$31,"OP") -> 0 | C33: =COUNTIFS('FORM G1'!$K$14:$K$31,'FORM G2'!$A$16:$A$33,'FORM G1'!$Q$14:$Q$31,"TESS") -> 0 | D33: =COUNTIFS('FORM G1'!$K$14:$K$31,'FORM G2'!$A$16:$A$33,'FORM G1'!$Q$14:$Q$31,"TESS/OP") -> 0 | E33: =SUM(B33:D33) -> 0 | F33: =SUMIF('FORM G1'!$K$14:$K$31,'FORM G2'!$A$16:$A$33,'FORM G1'!$O$14:$O$31) -> 0 | G33: 0 | I33: =F33+H33 -> 0
C35: TOTALS TO FORM E | E35: =SUM(E16:E33) -> 9 | F35: - | I35: =SUM(I16:I33) -> 1889.34
A38: * Penalty codes & fines
A40: Codes | B40: Description | E40: Pen Amount | F40: Pen % | G40: Min Penalty | I40: Double Penalty
A41: 1 | B41: FAILED TO OPERATE | F41: 0.4 | G41: 100 | I41: YES
A42: 2 | B42: LATE > 5 MIN | F42: 0.25 | I42: YES
A43: 3 | B43: LATE > 15 MIN | F43: 0.4 | I43: YES
A44: 4 | B44: LATE > 30 MIN | F44: 0 | I44: YES
A45: 5 | B45: TRIP OPERATED EARLY | F45: 0.4 | I45: YES
A46: 6 | B46: BREAKDOWN OR LATE REPLACEMENT | F46: 0.4 | I46: No
A47: 7 | B47: INCORRECT OR NO DESTINATION SHOWN | E47: 100 | F47: 0 | I47: No
A48: 8 | B48: INCORRECT OR NO DUTY DISPLAYED | E48: 200 | F48: 0 | I48: No
A49: 9 | B49: FAILED TO STOP AND LOAD | E49: 60 | F49: 0 | I49: No
A50: 10.1 | B50: VEHICLE - DIRTY | E50: 30 | F50: 0 | I50: No
A51: 10.2 | B51: VEHICLE - BROKEN WINDOWS | E51: 120 | F51: 0 | I51: No
A52: 10.3 | B52: VEHICLE - SEATS TORN/BROKEN | E52: 30 | F52: 0 | I52: No
A53: 10.4 | B53: VEHICLE - DOOR BROKEN/MISSING | E53: 120 | F53: 0 | I53: No
A54: 11 | B54: DEVIATION FROM ROUTE | E54: 100 | F54: 0 | I54: No
A55: 12 | B55: NO HEAD/REAR LIGHTS | E55: 100 | F55: 0 | I55: No
A56: 13 | B56: APPROVED EE NOT USED | F56: 0.03 | I56: No
A57: 14 | B57: COF - TIME DNO | F57: 0 | I57: No
A58: 15 | B58: BUS DNO | F58: 0.4 | I58: No

Sheet FORM I1 SUB STD NORMAL
B1: FORM I1 - STANDARD BUS NORMAL
B3: PUBLIC TRANSPORT : | D3: ='FORM A'!C3 -> PROVISION OF PUBLIC PASSENGER TRANSPORT MKUZE AND SURROUNDING
B5: ='FORM A'!A6 -> CONTRACT : ZNT 1129 | G5: OPERATOR : | I5: ='FORM A'!F6 -> Ripple Effect 40 (Pty) Ltd
B7: PAYMENT CERTIFICATE NO.: | E7: ='FORM A'!C8 -> 320 | G7: FOR MONTH: | I7: ='FORM A'!F8 -> 45778
B9: TRIPS PER MONTH - CALCULATION SHEET FOR SUBSIDISED SERVICES
B11: Route No | C11: F/R | D11: From | E11: To | F11: Route Length | G11: Number of scheduled trips per day | O11: TOTAL Sched Trips | P11: TOTAL Sched Km
G13: Mon | H13: Tue | I13: Wed | J13: Thurs | K13: Fri | L13: Sat | M13: Sun | N13: Pub
B15: 1 | C15: 2 | D15: 3 | E15: 4 | F15: 5 | G15: 6 | H15: 7 | I15: 8 | J15: 9 | K15: 10 | L15: 11 | M15: 12 | N15: =M15+1 -> 13 | O15: 13 | P15: 14 | Q15: OPS | R15: SK
A16: =CONCATENATE(B16,C16) -> 10F | B16: 10 | C16: F | D16: BIVA TERMINUS | E16: PONGOLA TERMINUS | F16: 101.5 | G16: 1 | H16: 1 | I16: 1 | J16: 1 | K16: 1 | L16: 1 | M16: 0 | N16: 0 | O16: =(G16*$G$58)+(H16*$H$58)+(I16*$I$58)+(J16*$J$58)+(K16*$K$58)+(L16*$L$58)+(M16*$M$58)+(N16*$N$58) -> 26 | P16: =F16*O16 -> 2639 | Q16: =VLOOKUP(A16,[3]Sheet1!$A$4:$B$43,2,FALSE) -> 23 | R16: =O16-Q16 -> 3
A17: =CONCATENATE(B17,C17) -> 10R | B17: 10 | C17: R | D17: PONGOLA TERMINUS | E17: BIVA TERMINUS | F17: 101.5 | G17: 1 | H17: 1 | I17: 1 | J17: 1 | K17: 1 | L17: 1 | M17: 0 | N17: 0 | O17: =(G17*$G$58)+(H17*$H$58)+(I17*$I$58)+(J17*$J$58)+(K17*$K$58)+(L17*$L$58)+(M17*$M$58)+(N17*$N$58) -> 26 | P17: =F17*O17 -> 2639 | Q17: =VLOOKUP(A17,[3]Sheet1!$A$4:$B$43,2,FALSE) -> 23 | R17: =O17-Q17 -> 3
A18: =CONCATENATE(B18,C18) -> 1A.3F | B18: 1A.3 | C18: F | D18: INGWAVUMA | E18: MKUZE | F18: 73.8 | G18: 0 | H18: 0 | I18: 0 | J18: 0 | K18: 0 | L18: 0 | M18: 1 | N18: 1 | O18: =(G18*$G$58)+(H18*$H$58)+(I18*$I$58)+(J18*$J$58)+(K18*$K$58)+(L18*$L$58)+(M18*$M$58)+(N18*$N$58) -> 5 | P18: =F18*O18 -> 369 | Q18: =VLOOKUP(A18,[3]Sheet1!$A$4:$B$43,2,FALSE) -> 4 | R18: =O18-Q18 -> 1
A19: =CONCATENATE(B19,C19) -> 1A.3R | B19: 1A.3 | C19: R | D19: MKUZE | E19: INGWAVUMA | F19: 73.8 | G19: 0 | H19: 0 | I19: 0 | J19: 0 | K19: 0 | L19: 0 | M19: 1 | N19: 1 | O19: =(G19*$G$58)+(H19*$H$58)+(I19*$I$58)+(J19*$J$58)+(K19*$K$58)+(L19*$L$58)+(M19*$M$58)+(N19*$N$58) -> 5 | P19: =F19*O19 -> 369 | Q19: =VLOOKUP(A19,[3]Sheet1!$A$4:$B$43,2,FALSE) -> 4 | R19: =O19-Q19 -> 1
A20: =CONCATENATE(B20,C20) -> 1A1F | B20: 1A1 | C20: F | D20: INGWAVUMA | E20: MKUZE | F20: 81.8 | G20: 1 | H20: 1 | I20: 1 | J20: 1 | K20: 1 | L20: 1 | M20: 0 | N20: 0 | O20: =(G20*$G$58)+(H20*$H$58)+(I20*$I$58)+(J20*$J$58)+(K20*$K$58)+(L20*$L$58)+(M20*$M$58)+(N20*$N$58) -> 26 | P20: =F20*O20 -> 2126.8 | Q20: =VLOOKUP(A20,[3]Sheet1!$A$4:$B$43,2,FALSE) -> 21 | R20: =O20-Q20 -> 5
A21: =CONCATENATE(B21,C21) -> 1A1R | B21: 1A1 | C21: R | D21: MKUZE | E21: INGWAVUMA | F21: 90 | G21: 1 | H21: 1 | I21: 1 | J21: 1 | K21: 1 | L21: 1 | M21: 0 | N21: 0 | O21: =(G21*$G$58)+(H21*$H$58)+(I21*$I$58)+(J21*$J$58)+(K21*$K$58)+(L21*$L$58)+(M21*$M$58)+(N21*$N$58) -> 26 | P21: =F21*O21 -> 2340 | Q21: =VLOOKUP(A21,[3]Sheet1!$A$4:$B$43,2,FALSE) -> 17 | R21: =O21-Q21 -> 9
A22: =CONCATENATE(B22,C22) -> 1A4F | B22: 1A4 | C22: F | D22: MAVELA | E22: MKUZE | F22: 35.8 | G22: 1 | H22: 1 | I22: 1 | J22: 1 | K22: 1 | L22: 1 | M22: 0 | N22: 0 | O22: =(G22*$G$58)+(H22*$H$58)+(I22*$I$58)+(J22*$J$58)+(K22*$K$58)+(L22*$L$58)+(M22*$M$58)+(N22*$N$58) -> 26 | P22: =F22*O22 -> 930.8 | Q22: =VLOOKUP(A22,[3]Sheet1!$A$4:$B$43,2,FALSE) -> 22 | R22: =O22-Q22 -> 4
A23: =CONCATENATE(B23,C23) -> 1A4R | B23: 1A4 | C23: R | D23: MKUZE | E23: MAVELA | F23: 35.8 | G23: 1 | H23: 1 | I23: 1 | J23: 1 | K23: 1 | L23: 1 | M23: 0 | N23: 0 | O23: =(G23*$G$58)+(H23*$H$58)+(I23*$I$58)+(J23*$J$58)+(K23*$K$58)+(L23*$L$58)+(M23*$M$58)+(N23*$N$58) -> 26 | P23: =F23*O23 -> 930.8 | Q23: =VLOOKUP(A23,[3]Sheet1!$A$4:$B$43,2,FALSE) -> 23 | R23: =O23-Q23 -> 3
A24: =CONCATENATE(B24,C24) -> 1B.1F | B24: 1B.1 | C24: F | D24: INGWAVUMA | E24: MKUZE | F24: 90 | G24: 1 | H24: 1 | I24: 1 | J24: 1 | K24: 1 | L24: 1 | M24: 1 | N24: 1 | O24: =(G24*$G$58)+(H24*$H$58)+(I24*$I$58)+(J24*$J$58)+(K24*$K$58)+(L24*$L$58)+(M24*$M$58)+(N24*$N$58) -> 31 | P24: =F24*O24 -> 2790 | Q24: =VLOOKUP(A24,[3]Sheet1!$A$4:$B$43,2,FALSE) -> 21 | R24: =O24-Q24 -> 10
A25: =CONCATENATE(B25,C25) -> 1B.1R | B25: 1B.1 | C25: R | D25: MKUZE | E25: INGWAVUMA | F25: 90 | G25: 1 | H25: 1 | I25: 1 | J25: 1 | K25: 1 | L25: 1 | M25: 1 | N25: 1 | O25: =(G25*$G$58)+(H25*$H$58)+(I25*$I$58)+(J25*$J$58)+(K25*$K$58)+(L25*$L$58)+(M25*$M$58)+(N25*$N$58) -> 31 | P25: =F25*O25 -> 2790 | Q25: =VLOOKUP(A25,[3]Sheet1!$A$4:$B$43,2,FALSE) -> 27 | R25: =O25-Q25 -> 4
A26: =CONCATENATE(B26,C26) -> 1B2F | B26: 1B2 | C26: F | D26: INGWAVUMA | E26: MKUZE | F26: 85.3 | G26: 1 | H26: 1 | I26: 1 | J26: 1 | K26: 1 | L26: 1 | M26: 0 | N26: 0 | O26: =(G26*$G$58)+(H26*$H$58)+(I26*$I$58)+(J26*$J$58)+(K26*$K$58)+(L26*$L$58)+(M26*$M$58)+(N26*$N$58) -> 26 | P26: =F26*O26 -> 2217.8 | Q26: =VLOOKUP(A26,[3]Sheet1!$A$4:$B$43,2,FALSE) -> 23 | R26: =O26-Q26 -> 3
A27: =CONCATENATE(B27,C27) -> 1B2R | B27: 1B2 | C27: R | D27: MKUZE | E27: INGWAVUMA | F27: 85.3 | G27: 1 | H27: 1 | I27: 1 | J27: 1 | K27: 1 | L27: 1 | M27: 0 | N27: 0 | O27: =(G27*$G$58)+(H27*$H$58)+(I27*$I$58)+(J27*$J$58)+(K27*$K$58)+(L27*$L$58)+(M27*$M$58)+(N27*$N$58) -> 26 | P27: =F27*O27 -> 2217.8 | Q27: =VLOOKUP(A27,[3]Sheet1!$A$4:$B$43,2,FALSE) -> 22 | R27: =O27-Q27 -> 4
... A55: =CONCATENATE(B55,C55) -> 9BR | B55: 9B | C55: R | D55: MKUZE TERMINUS | E55: HLABISATERMINUS | F55: 78 | G55: 1 | H55: 1 | I55: 1 | J55: 1 | K55: 1 | L55: 1 | M55: 0 | N55: 0 | O55: =(G55*$G$58)+(H55*$H$58)+(I55*$I$58)+(J55*$J$58)+(K55*$K$58)+(L55*$L$58)+(M55*$M$58)+(N55*$N$58) -> 26 | P55: =F55*O55 -> 2028 | Q55: =VLOOKUP(A55,[3]Sheet1!$A$4:$B$43,2,FALSE) -> 23 | R55: =O55-Q55 -> 3
D57: Total number of trips per day | G57: =SUM(G16:G56) -> 38 | H57: =SUM(H16:H56) -> 38 | I57: =SUM(I16:I56) -> 38 | J57: =SUM(J16:J56) -> 38 | K57: =SUM(K16:K56) -> 36 | L57: =SUM(L16:L56) -> 33 | M57: =SUM(M16:M56) -> 9 | N57: =SUM(N16:N56) -> 9 | ... P57: =SUM(P16:P56) -> 82763.4
D58: Number of days per claim period | G58: 4 | H58: 4 | I58: 4 | J58: 4 | K58: 5 | L58: 5 | M58: 4 | N58: 1
O62: =O57+#REF! -> #REF!
O64: =SUM(G58:N58) -> 31

Sheet FORM I2 UNSUB STD 
B1: FORM I1 - STANDARD BUS NORMAL
B3: PUBLIC TRANSPORT : | D3: ='FORM A'!C3 -> PROVISION OF PUBLIC PASSENGER TRANSPORT MKUZE AND SURROUNDING
B5: ='FORM A'!A6 -> CONTRACT : ZNT 1129 | G5: OPERATOR : | I5: ='FORM A'!F6 -> Ripple Effect 40 (Pty) Ltd
B7: PAYMENT CERTIFICATE NO.: | E7: ='FORM A'!C8 -> 320 | G7: FOR MONTH: | I7: ='FORM A'!F8 -> 45778
B9: TRIPS PER MONTH - CALCULATION SHEET FOR SUBSIDISED SERVICES
B11: Route No | C11: F/R | D11: From | E11: To | F11: Route Length | G11: Number of scheduled trips per day | O11: TOTAL Sched Trips | P11: TOTAL Sched Km
G13: Mon | H13: Tue | I13: Wed | J13: Thurs | K13: Fri | L13: Sat | M13: Sun | N13: Pub
B15: 1 | C15: 2 | D15: 3 | E15: 4 | F15: 5 | G15: 6 | H15: 7 | I15: 8 | J15: 9 | K15: 10 | L15: 11 | M15: 12 | N15: =M15+1 -> 13 | O15: 13 | P15: 14
A16: =CONCATENATE(B16,C16) -> 4R | B16: 4 | C16: R | D16: MANGUZI | E16: INGWAVUMA | F16: 98.9 | G16: 2 | H16: 2 | I16: 2 | J16: 2 | K16: 2 | O16: =(G16*$G$23)+(H16*$H$23)+(I16*$I$23)+(J16*$J$23)+(K16*$K$23)+(L16*$L$23)+(M16*$M$23)+(N16*$N$23) -> 42 | P16: =F16*O16 -> 4153.8 | R16: =ROUND(F16,1) -> 98.9
A17: =CONCATENATE(B17,C17) -> 8F | B17: 8 | C17: F | D17: MANABA | E17: MKUZE | F17: 78.8 | K17: 2 | O17: =(G17*$G$23)+(H17*$H$23)+(I17*$I$23)+(J17*$J$23)+(K17*$K$23)+(L17*$L$23)+(M17*$M$23)+(N17*$N$23) -> 10 | P17: =F17*O17 -> 788
A18: =CONCATENATE(B18,C18) -> 11AR | B18: 11A | C18: R | D18: MKUZE | E18: EMPANGENI | F18: 125.6 | G18: 2 | H18: 2 | I18: 2 | J18: 2 | K18: 2 | O18: =(G18*$G$23)+(H18*$H$23)+(I18*$I$23)+(J18*$J$23)+(K18*$K$23)+(L18*$L$23)+(M18*$M$23)+(N18*$N$23) -> 42 | P18: =F18*O18 -> 5275.2
A19: =CONCATENATE(B19,C19) -> 11BF | B19: 11B | C19: F | D19: MANABA | E19: EMPANGENI | F19: 224.9 | K19: 2 | M19: 2 | O19: =(G19*$G$23)+(H19*$H$23)+(I19*$I$23)+(J19*$J$23)+(K19*$K$23)+(L19*$L$23)+(M19*$M$23)+(N19*$N$23) -> 18 | P19: =F19*O19 -> 4048.2
A20: =CONCATENATE(B20,C20) -> 19AR | B20: 19A | C20: R | D20: MKUZE | E20: MHLEKAZI | F20: 40 | G20: 2 | H20: 2 | I20: 2 | J20: 2 | K20: 2 | L20: 2 | O20: =(G20*$G$23)+(H20*$H$23)+(I20*$I$23)+(J20*$J$23)+(K20*$K$23)+(L20*$L$23)+(M20*$M$23)+(N20*$N$23) -> 52 | P20: =F20*O20 -> 2080
D22: Total number of trips per day | G22: =SUM(G16:G21) -> 6 | H22: =SUM(H16:H21) -> 6 | I22: =SUM(I16:I21) -> 6 | J22: =SUM(J16:J21) -> 6 | K22: =SUM(K16:K21) -> 10 | L22: =SUM(L16:L21) -> 2 | M22: =SUM(M16:M21) -> 2 | N22: =SUM(N16:N21) -> 0 | ... P22: =SUM(P16:P21) -> 16345.2
D23: Number of days per claim period | G23: ='FORM I1 SUB STD NORMAL'!G58 -> 4 | H23: ='FORM I1 SUB STD NORMAL'!H58 -> 4 | I23: ='FORM I1 SUB STD NORMAL'!I58 -> 4 | J23: ='FORM I1 SUB STD NORMAL'!J58 -> 4 | K23: ='FORM I1 SUB STD NORMAL'!K58 -> 5 | L23: ='FORM I1 SUB STD NORMAL'!L58 -> 5 | M23: ='FORM I1 SUB STD NORMAL'!M58 -> 4 | N23: ='FORM I1 SUB STD NORMAL'!N58 -> 1

Sheet FORM I1 SUB STD NORMAL SK
B1: FORM I1 - STANDARD BUS NORMAL
B3: PUBLIC TRANSPORT : | D3: ='FORM A'!C3 -> PROVISION OF PUBLIC PASSENGER TRANSPORT MKUZE AND SURROUNDING
B5: ='FORM A'!A6 -> CONTRACT : ZNT 1129 | G5: OPERATOR : | I5: ='FORM A'!F6 -> Ripple Effect 40 (Pty) Ltd
B7: PAYMENT CERTIFICATE NO.: | E7: ='FORM A'!C8 -> 320 | G7: FOR MONTH: | I7: ='FORM A'!F8 -> 45778
B9: TRIPS PER MONTH - CALCULATION SHEET FOR SUBSIDISED SERVICES
B11: Route No | C11: F/R | D11: From | E11: To | F11: Route Length | G11: Number of scheduled trips per day | O11: TOTAL Sched Trips | P11: TOTAL Sched Km
G13: Mon | H13: Tue | I13: Wed | J13: Thurs | K13: Fri | L13: Sat | M13: Sun | N13: Pub
B15: 1 | C15: 2 | D15: 3 | E15: 4 | F15: 5 | G15: 6 | H15: 7 | I15: 8 | J15: 9 | K15: 10 | L15: 11 | M15: 12 | N15: =M15+1 -> 13 | O15: 13 | P15: 14 | Q15: OPS | R15: SK
A16: =CONCATENATE(B16,C16) -> 10F | B16: 10 | C16: F | D16: BIVA TERMINUS | E16: PONGOLA TERMINUS | F16: 101.5 | G16: 1 | H16: 1 | I16: 1 | J16: 1 | K16: 1 | L16: 1 | M16: 0 | N16: 0 | O16: =(G16*$G$58)+(H16*$H$58)+(I16*$I$58)+(J16*$J$58)+(K16*$K$58)+(L16*$L$58)+(M16*$M$58)+(N16*$N$58) -> 0 | P16: =F16*O16 -> 0 | Q16: =VLOOKUP(A16,[3]Sheet1!$A$4:$B$43,2,FALSE) -> 23 | R16: =O16-Q16 -> -23
A17: =CONCATENATE(B17,C17) -> 10R | B17: 10 | C17: R | D17: PONGOLA TERMINUS | E17: BIVA TERMINUS | F17: 101.5 | G17: 1 | H17: 1 | I17: 1 | J17: 1 | K17: 1 | L17: 1 | M17: 0 | N17: 0 | O17: =(G17*$G$58)+(H17*$H$58)+(I17*$I$58)+(J17*$J$58)+(K17*$K$58)+(L17*$L$58)+(M17*$M$58)+(N17*$N$58) -> 0 | P17: =F17*O17 -> 0 | Q17: =VLOOKUP(A17,[3]Sheet1!$A$4:$B$43,2,FALSE) -> 23 | R17: =O17-Q17 -> -23
A18: =CONCATENATE(B18,C18) -> 1A.3F | B18: 1A.3 | C18: F | D18: INGWAVUMA | E18: MKUZE | F18: 73.8 | G18: 0 | H18: 0 | I18: 0 | J18: 0 | K18: 0 | L18: 0 | M18: 1 | N18: 1 | O18: =(G18*$G$58)+(H18*$H$58)+(I18*$I$58)+(J18*$J$58)+(K18*$K$58)+(L18*$L$58)+(M18*$M$58)+(N18*$N$58) -> 0 | P18: =F18*O18 -> 0 | Q18: =VLOOKUP(A18,[3]Sheet1!$A$4:$B$43,2,FALSE) -> 4 | R18: =O18-Q18 -> -4
A19: =CONCATENATE(B19,C19) -> 1A.3R | B19: 1A.3 | C19: R | D19: MKUZE | E19: INGWAVUMA | F19: 73.8 | G19: 0 | H19: 0 | I19: 0 | J19: 0 | K19: 0 | L19: 0 | M19: 1 | N19: 1 | O19: =(G19*$G$58)+(H19*$H$58)+(I19*$I$58)+(J19*$J$58)+(K19*$K$58)+(L19*$L$58)+(M19*$M$58)+(N19*$N$58) -> 0 | P19: =F19*O19 -> 0 | Q19: =VLOOKUP(A19,[3]Sheet1!$A$4:$B$43,2,FALSE) -> 4 | R19: =O19-Q19 -> -4
A20: =CONCATENATE(B20,C20) -> 1A1F | B20: 1A1 | C20: F | D20: INGWAVUMA | E20: MKUZE | F20: 81.8 | G20: 1 | H20: 1 | I20: 1 | J20: 1 | K20: 1 | L20: 1 | M20: 0 | N20: 0 | O20: =(G20*$G$58)+(H20*$H$58)+(I20*$I$58)+(J20*$J$58)+(K20*$K$58)+(L20*$L$58)+(M20*$M$58)+(N20*$N$58) -> 0 | P20: =F20*O20 -> 0 | Q20: =VLOOKUP(A20,[3]Sheet1!$A$4:$B$43,2,FALSE) -> 21 | R20: =O20-Q20 -> -21
A21: =CONCATENATE(B21,C21) -> 1A1R | B21: 1A1 | C21: R | D21: MKUZE | E21: INGWAVUMA | F21: 90 | G21: 1 | H21: 1 | I21: 1 | J21: 1 | K21: 1 | L21: 1 | M21: 0 | N21: 0 | O21: =(G21*$G$58)+(H21*$H$58)+(I21*$I$58)+(J21*$J$58)+(K21*$K$58)+(L21*$L$58)+(M21*$M$58)+(N21*$N$58) -> 0 | P21: =F21*O21 -> 0 | Q21: =VLOOKUP(A21,[3]Sheet1!$A$4:$B$43,2,FALSE) -> 17 | R21: =O21-Q21 -> -17
A22: =CONCATENATE(B22,C22) -> 1A4F | B22: 1A4 | C22: F | D22: MAVELA | E22: MKUZE | F22: 35.8 | G22: 1 | H22: 1 | I22: 1 | J22: 1 | K22: 1 | L22: 1 | M22: 0 | N22: 0 | O22: =(G22*$G$58)+(H22*$H$58)+(I22*$I$58)+(J22*$J$58)+(K22*$K$58)+(L22*$L$58)+(M22*$M$58)+(N22*$N$58) -> 0 | P22: =F22*O22 -> 0 | Q22: =VLOOKUP(A22,[3]Sheet1!$A$4:$B$43,2,FALSE) -> 22 | R22: =O22-Q22 -> -22
A23: =CONCATENATE(B23,C23) -> 1A4R | B23: 1A4 | C23: R | D23: MKUZE | E23: MAVELA | F23: 35.8 | G23: 1 | H23: 1 | I23: 1 | J23: 1 | K23: 1 | L23: 1 | M23: 0 | N23: 0 | O23: =(G23*$G$58)+(H23*$H$58)+(I23*$I$58)+(J23*$J$58)+(K23*$K$58)+(L23*$L$58)+(M23*$M$58)+(N23*$N$58) -> 0 | P23: =F23*O23 -> 0 | Q23: =VLOOKUP(A23,[3]Sheet1!$A$4:$B$43,2,FALSE) -> 23 | R23: =O23-Q23 -> -23
A24: =CONCATENATE(B24,C24) -> 1B.1F | B24: 1B.1 | C24: F | D24: INGWAVUMA | E24: MKUZE | F24: 90 | G24: 1 | H24: 1 | I24: 1 | J24: 1 | K24: 1 | L24: 1 | M24: 1 | N24: 1 | O24: =(G24*$G$58)+(H24*$H$58)+(I24*$I$58)+(J24*$J$58)+(K24*$K$58)+(L24*$L$58)+(M24*$M$58)+(N24*$N$58) -> 0 | P24: =F24*O24 -> 0 | Q24: =VLOOKUP(A24,[3]Sheet1!$A$4:$B$43,2,FALSE) -> 21 | R24: =O24-Q24 -> -21
A25: =CONCATENATE(B25,C25) -> 1B.1R | B25: 1B.1 | C25: R | D25: MKUZE | E25: INGWAVUMA | F25: 90 | G25: 1 | H25: 1 | I25: 1 | J25: 1 | K25: 1 | L25: 1 | M25: 1 | N25: 1 | O25: =(G25*$G$58)+(H25*$H$58)+(I25*$I$58)+(J25*$J$58)+(K25*$K$58)+(L25*$L$58)+(M25*$M$58)+(N25*$N$58) -> 0 | P25: =F25*O25 -> 0 | Q25: =VLOOKUP(A25,[3]Sheet1!$A$4:$B$43,2,FALSE) -> 27 | R25: =O25-Q25 -> -27
A26: =CONCATENATE(B26,C26) -> 1B2F | B26: 1B2 | C26: F | D26: INGWAVUMA | E26: MKUZE | F26: 85.3 | G26: 1 | H26: 1 | I26: 1 | J26: 1 | K26: 1 | L26: 1 | M26: 0 | N26: 0 | O26: =(G26*$G$58)+(H26*$H$58)+(I26*$I$58)+(J26*$J$58)+(K26*$K$58)+(L26*$L$58)+(M26*$M$58)+(N26*$N$58) -> 0 | P26: =F26*O26 -> 0 | Q26: =VLOOKUP(A26,[3]Sheet1!$A$4:$B$43,2,FALSE) -> 23 | R26: =O26-Q26 -> -23
A27: =CONCATENATE(B27,C27) -> 1B2R | B27: 1B2 | C27: R | D27: MKUZE | E27: INGWAVUMA | F27: 85.3 | G27: 1 | H27: 1 | I27: 1 | J27: 1 | K27: 1 | L27: 1 | M27: 0 | N27: 0 | O27: =(G27*$G$58)+(H27*$H$58)+(I27*$I$58)+(J27*$J$58)+(K27*$K$58)+(L27*$L$58)+(M27*$M$58)+(N27*$N$58) -> 0 | P27: =F27*O27 -> 0 | Q27: =VLOOKUP(A27,[3]Sheet1!$A$4:$B$43,2,FALSE) -> 22 | R27: =O27-Q27 -> -22
... A55: =CONCATENATE(B55,C55) -> 9BR | B55: 9B | C55: R | D55: MKUZE TERMINUS | E55: HLABISATERMINUS | F55: 78 | G55: 1 | H55: 1 | I55: 1 | J55: 1 | K55: 1 | L55: 1 | M55: 0 | N55: 0 | O55: =(G55*$G$58)+(H55*$H$58)+(I55*$I$58)+(J55*$J$58)+(K55*$K$58)+(L55*$L$58)+(M55*$M$58)+(N55*$N$58) -> 0 | P55: =F55*O55 -> 0 | Q55: =VLOOKUP(A55,[3]Sheet1!$A$4:$B$43,2,FALSE) -> 23 | R55: =O55-Q55 -> -23
D57: Total number of trips per day | G57: =SUM(G16:G56) -> 38 | H57: =SUM(H16:H56) -> 38 | I57: =SUM(I16:I56) -> 38 | J57: =SUM(J16:J56) -> 38 | K57: =SUM(K16:K56) -> 36 | L57: =SUM(L16:L56) -> 33 | M57: =SUM(M16:M56) -> 9 | N57: =SUM(N16:N56) -> 9 | ... P57: =SUM(P16:P56) -> 0
D58: Number of days per claim period | G58: 0 | H58: 0 | I58: 0 | J58: 0 | K58: 0 | L58: 0 | M58: 0 | N58: 0
O62: =O57+#REF! -> #REF! | P62: =P57+#REF! -> #REF!
